ICC2008_priliminary_grad_cell_data/icc2008/lcd_ctrl.v

module LCD_CTRL(clk, reset, datain, cmd, cmd_valid, dataout, output_valid, busy);
input           clk;
input           reset;
input   [7:0]   datain;
input   [3:0]   cmd;
input           cmd_valid;
output reg [7:0]   dataout;
output reg         output_valid;
output reg        busy;

reg [7:0] map[107:0];
reg [3:0] originx;
reg [3:0] originy;
reg zoom;
reg [1:0] rot;
reg state;
reg [6:0] cnt;
reg [4:0] discnt;

always @(posedge clk or posedge reset) 
begin
    if(reset)
    begin
       state <= 1;
        busy <= 0;
        output_valid <= 0;
        rot <= 0;
        originx <= 4;
        originy <= 3;
        cnt <= 0;
        zoom <= 0;
        discnt <= 0;
    end


    else
    begin
        if((cmd_valid == 1 && busy == 0 && cmd == 0) || state == 0)  //load
        begin
            
            if(state == 1)
            begin
                state = 0;
                cnt = 0;
            end

            else if(cnt == 108)
            begin
                rot = 0;
                cnt = 0;
                state = 1;
            end
            
            else
            begin
                busy = 1;
                map[cnt] = datain;
                cnt = cnt + 1;
                state = 0;
            end

        end

        else if(cmd_valid == 1 && busy == 0 && cmd == 1)  //rotate left
        begin
            if(zoom == 0)
            rot = rot - 1;

            state = 1;
            busy = 1;
        end

        else if(cmd_valid == 1 && busy == 0 && cmd == 2) //rotate right
        begin
            if(zoom == 0)
            rot = rot + 1;

            state = 1;
            busy = 1;
        end

        else if(cmd_valid == 1 && busy == 0 && cmd == 3)  //zoom in
        begin
           originx = 4;
           originy = 3;
           zoom = 1;
           state = 1;
           busy = 1;
        end

        else if(cmd_valid == 1 && busy == 0 && cmd == 4) //zoom fit
        begin
           zoom = 0;
           state = 1;
           busy = 1;
        end

        else if(cmd_valid == 1 && busy == 0 && cmd == 5) //shift right
        begin
           if(zoom == 1)
           begin
           if(rot == 0 || rot == 2)
           begin
               if(originx >= 8)
               originx = 8;
               else
               originx = originx + 1;
           end
           else if(rot == 3)
           begin
                if(originy >= 5)
                originy = 5;
                else
                originy = originy + 1;
           end
           else if(rot == 1)
            begin
                if(originy <= 0)
                originy = 0;
                else
                originy = originy - 1;
            end
           end
           state = 1;
           busy = 1;
        end

        else if(cmd_valid == 1 && busy == 0 && cmd == 6) 
        begin
         if(zoom == 1)
         begin
           if(rot == 0 || rot == 2)
           begin
               if(originx <= 0)
               originx = 0;
               else
               originx = originx - 1;
           end
           else if(rot == 3)
           begin
                if(originy <= 0)
                originy = 0;
                else
                originy = originy - 1;
           end
           else if(rot == 1)
            begin
                if(originy >= 5)
                originy = 5;
                else
                originy = originy + 1;
            end
         end
           state = 1;
           busy = 1;
        end

        else if(cmd_valid == 1 && busy == 0 && cmd == 7) 
        begin
        if(zoom == 1)
        begin
           if(rot == 0 || rot == 2)
           begin
               if(originy <= 0)
               originy = 0;
               else
               originy = originy - 1;
           end
           else if(rot == 3)
           begin
                if(originx >= 8)
                originx = 8;
                else
                originx = originx + 1;
           end
           else if(rot == 1)
            begin
                if(originx <= 0)
                originx = 0;
                else
                originx = originx - 1;
            end

        end

           state = 1;
           busy = 1;
        end

        else if(cmd_valid == 1 && busy == 0 && cmd == 8) 
        begin
        if(zoom == 1)
        begin
           if(rot == 0 || rot == 2)
           begin
               if(originy >= 5)
               originy = 5;
               else
               originy = originy + 1;
           end
           else if(rot == 3)
           begin
                if(originx <= 0)
                originx = 0;
                else
                originx = originx - 1;
           end
           else if(rot == 1)
            begin
                if(originx >= 8)
                originx = 8;
                else
                originx = originx + 1;
            end
        end
           state = 1;
           busy = 1;
        end
    end
end


always @(posedge clk) 
begin
    if(state == 1 && busy == 1)
    begin
        if(zoom == 0)
        begin
            output_valid = 1;

            if(discnt == 16)
            begin
                discnt = 0;
                state = 1;
                output_valid = 0;
                busy = 0;
            end

            else
            begin
            if(rot == 0 || rot == 2)
            begin
                case(discnt)
                0:dataout = map[13];
                1:dataout = map[16];
                2:dataout = map[19];
                3:dataout = map[22];
                4:dataout = map[37];
                5:dataout = map[40];
                6:dataout = map[43];
                7:dataout = map[46];
                8:dataout = map[61];
                9:dataout = map[64];
                10:dataout = map[67];
                11:dataout = map[70];
                12:dataout = map[85];
                13:dataout = map[88];
                14:dataout = map[91];
                15:dataout = map[94];
                endcase
            end

            else if(rot == 3)
            begin
                case(discnt)
                12:dataout = map[13];
                8:dataout = map[16];
                4:dataout = map[19];
                0:dataout = map[22];
                13:dataout = map[37];
                9:dataout = map[40];
                5:dataout = map[43];
                1:dataout = map[46];
                14:dataout = map[61];
                10:dataout = map[64];
                6:dataout = map[67];
                2:dataout = map[70];
                15:dataout = map[85];
                11:dataout = map[88];
                7:dataout = map[91];
                3:dataout = map[94];
                endcase
            end

            else if(rot == 1)
            begin
                case(discnt)
                3:dataout = map[13];
                7:dataout = map[16];
                11:dataout = map[19];
                15:dataout = map[22];
                2:dataout = map[37];
                6:dataout = map[40];
                10:dataout = map[43];
                14:dataout = map[46];
                1:dataout = map[61];
                5:dataout = map[64];
                9:dataout = map[67];
                13:dataout = map[70];
                0:dataout = map[85];
                4:dataout = map[88];
                8:dataout = map[91];
                12:dataout = map[94];
                endcase  
            end
                discnt = discnt + 1; 
            end
        end

        else
        begin
            output_valid = 1;
            if(discnt == 16)
            begin
                discnt = 0;
                state = 1;
                output_valid = 0;
                busy = 0;
            end

            else
            begin
                if(rot == 0 || rot == 2)
                begin
                   case(discnt)
                    0:dataout = map[originy*12+originx];
                    1:dataout = map[originy*12+originx+1];
                    2:dataout = map[originy*12+originx+2];
                    3:dataout = map[originy*12+originx+3];
                    4:dataout = map[(originy+1)*12+originx];
                    5:dataout = map[(originy+1)*12+originx+1];
                    6:dataout = map[(originy+1)*12+originx+2];
                    7:dataout = map[(originy+1)*12+originx+3];
                    8:dataout = map[(originy+2)*12+originx];
                    9:dataout = map[(originy+2)*12+originx+1];
                    10:dataout = map[(originy+2)*12+originx+2];
                    11:dataout = map[(originy+2)*12+originx+3];
                    12:dataout = map[(originy+3)*12+originx];
                    13:dataout = map[(originy+3)*12+originx+1];
                    14:dataout = map[(originy+3)*12+originx+2];
                    15:dataout = map[(originy+3)*12+originx+3];
                    endcase
                end

                else if(rot == 3)
                begin
                   case(discnt)
                    12:dataout = map[originy*12+originx];
                    8:dataout = map[originy*12+originx+1];
                    4:dataout = map[originy*12+originx+2];
                    0:dataout = map[originy*12+originx+3];
                    13:dataout = map[(originy+1)*12+originx];
                    9:dataout = map[(originy+1)*12+originx+1];
                    5:dataout = map[(originy+1)*12+originx+2];
                    1:dataout = map[(originy+1)*12+originx+3];
                    14:dataout = map[(originy+2)*12+originx];
                    10:dataout = map[(originy+2)*12+originx+1];
                    6:dataout = map[(originy+2)*12+originx+2];
                    2:dataout = map[(originy+2)*12+originx+3];
                    15:dataout = map[(originy+3)*12+originx];
                    11:dataout = map[(originy+3)*12+originx+1];
                    7:dataout = map[(originy+3)*12+originx+2];
                    3:dataout = map[(originy+3)*12+originx+3];
                    endcase
                end
                
                else if(rot == 1)
                begin
                    case(discnt)
                    3:dataout = map[originy*12+originx];
                    7:dataout = map[originy*12+originx+1];
                    11:dataout = map[originy*12+originx+2];
                    15:dataout = map[originy*12+originx+3];
                    2:dataout = map[(originy+1)*12+originx];
                    6:dataout = map[(originy+1)*12+originx+1];
                    10:dataout = map[(originy+1)*12+originx+2];
                    14:dataout = map[(originy+1)*12+originx+3];
                    1:dataout = map[(originy+2)*12+originx];
                    5:dataout = map[(originy+2)*12+originx+1];
                    9:dataout = map[(originy+2)*12+originx+2];
                    13:dataout = map[(originy+2)*12+originx+3];
                    0:dataout = map[(originy+3)*12+originx];
                    4:dataout = map[(originy+3)*12+originx+1];
                    8:dataout = map[(originy+3)*12+originx+2];
                    12:dataout = map[(originy+3)*12+originx+3];
                    endcase
                end
                discnt = discnt + 1;
            end
        end
    end
end



endmodule

ICC2008_priliminary_grad_cell_data/icc2008/testfixture.v
`timescale 1ns/10ps
`define CYCLE    100          	        // Modify your clock period here
`define SDFFILE  "./LCD_CTRL.sdf"	      // Modify your sdf file name
`define IMAGE    "./image1.dat"         // Modify your test image file: image1.dat or image2.dat
`define CMD      "./cmd1.dat"           // Modify your test cmd file: cmd1.dat or cmd2.dat
`define EXPECT   "./out_golden1.dat"    // Modify your output golden file: out_golden1.dat or out_golden2.dat

module test;
parameter IMAGE_N_PAT = 108;
parameter CMD_N_PAT = 130;
parameter OUT_LENGTH= 2080;
parameter t_reset = `CYCLE*2;

reg           clk;
reg           reset;
reg   [7:0]   datain;
reg   [3:0]   cmd;
reg           cmd_valid;
wire  [7:0]   dataout;
wire          output_valid;
wire          busy;

reg   [7:0]   image_mem [0:IMAGE_N_PAT-1];
reg   [3:0]   cmd_mem   [0:CMD_N_PAT-1];
reg   [7:0]   out_mem   [0:OUT_LENGTH-1];
reg   [7:0]   out_temp;


reg   [5:0]   show;
reg   [5:0]   verify;
integer       i, j, out_f, err, pass, pattern_num;
reg           over;

   LCD_CTRL top(.clk(clk), .reset(reset), .datain(datain), 
                .cmd(cmd), .cmd_valid(cmd_valid), .dataout(dataout), 
                .output_valid(output_valid), .busy(busy));          
   


//initial $sdf_annotate(`SDFFILE, top);

initial	$readmemh (`IMAGE,  image_mem);
initial	$readmemh (`CMD,    cmd_mem);
initial	$readmemh (`EXPECT, out_mem);

initial begin
   clk         = 1'b0;
   reset       = 1'b0;
   cmd_valid   = 1'b0;
   over        = 1'b0;
   pattern_num = 0;
   err         = 0;
   pass        = 0;             
   show        = 6'b111111;   
   verify      = 6'b0;
end

always begin #(`CYCLE/2) clk = ~clk; end

initial begin
$dumpfile("LCD_CTRL.vcd");
$dumpvars;
//$fsdbDumpfile("LCD_CTRL.fsdb");
//$fsdbDumpvars;

   out_f = $fopen("out.dat");
   if (out_f == 0) begin
        $display("Output file open error !");
        $finish;
   end
end


initial begin
   @(negedge clk)  reset = 1'b1;
   #t_reset        reset = 1'b0;
   
   @(negedge clk)    i=0;
   while (i <= CMD_N_PAT) begin               
      if(!busy) begin
        cmd = cmd_mem[i];
        cmd_valid = 1'b1;  
        
        if(cmd_mem[i] === 'd0) begin    //cmd: Load data        
           for(j=0; j<=IMAGE_N_PAT; j=j+1)begin
              @(negedge clk) datain = image_mem[j];
                             cmd = 'hz; cmd_valid = 1'b0;
           end
           i = i+1;
        end
        else begin                      //cmd: other command
           @(negedge clk) datain='hz; cmd_valid = 1'b0; i = i+1;
        end       
      end 
      else begin
         datain='hz; cmd = 'hz;  cmd_valid = 0;
         @(negedge clk);
      end               
    end                                       
end

always @(posedge clk)begin
   out_temp = out_mem[pattern_num];
   if(output_valid)begin
      $fdisplay(out_f,"%h", dataout);      
      if(dataout !== out_temp) begin
         $display("ERROR at %d:output %h !=expect %h ",pattern_num, dataout, out_temp);
         err = err + 1 ;          
      end            
      else if(dataout === out_temp)begin      
         pass = pass + 1 ;
      end      
      #1 pattern_num = pattern_num + 1;
   end
   if(pattern_num === OUT_LENGTH)  over = 1'b1;      
   
   if(show[0]==1 && pass=='d16   && i=='d1)begin
     show[0]=0;  verify[0]=1'b1;
     $display("-----------------------------------------------------\n");
     $display("Congratulations! The first  test you have passed!\n");   
     $display("-----------------------------------------------------\n");
   end
   if(show[1]==1 && pass=='d96  && i=='d6)begin
     show[1]=0; verify[1]=1'b1;
     $display("-----------------------------------------------------\n");
     $display("Congratulations! The second test you have passed!\n");   
     $display("-----------------------------------------------------\n");     
   end
   if(show[2]==1 && pass=='d176  && i=='d11)begin
     show[2]=0; verify[2]=1'b1;
     $display("-----------------------------------------------------\n");
     $display("Congratulations! The third  test you have passed!\n");   
     $display("-----------------------------------------------------\n");     
   end      
   if(show[3]==1 && pass=='d368  && i=='d23)begin
     show[3]=0; verify[3]=1'b1;
     $display("-----------------------------------------------------\n");
     $display("Congratulations! The fourth test you have passed!\n");   
     $display("-----------------------------------------------------\n");     
   end
   if(show[4]==1 && pass=='d1968  && i=='d123)begin
     show[4]=0; verify[4]=1'b1;
     $display("-----------------------------------------------------\n");   
     $display("Congratulations! The fifth test you have passed!\n");   
     $display("-----------------------------------------------------\n");     
   end
   if(show[5]==1 && pass=='d2080  && i=='d130)begin
     show[5]=0; verify[5]=1'b1;
     $display("-----------------------------------------------------\n");   
     $display("Congratulations! The sixth  test you have passed!\n");   
     $display("-----------------------------------------------------\n");     
   end
end


initial begin
      @(posedge over)      
      if(pass === 'd2080) begin
         $display("-----------------------------------------------------\n");
         $display("Congratulations! All data have been generated successfully!\n");
         $display("-------------------------PASS------------------------\n");
      end
      else begin
            $display("-----------------------------------------------------\n");
            $display("There are %d errors!\n", err);
            $display("-----------------------------------------------------\n");

            $display("---------------------SUMMARY-------------------------\n");
            if(!(|verify))   $display("All test you have no passed!\n");
            else begin
               if(verify[0]) $display("Congratulations! The first  test you have passed!\n");
               if(verify[1]) $display("Congratulations! The second test you have passed!\n"); 
               if(verify[2]) $display("Congratulations! The third  test you have passed!\n"); 
               if(verify[3]) $display("Congratulations! The fourth test you have passed!\n"); 
               if(verify[4]) $display("Congratulations! The fifth  test you have passed!\n"); 
               if(verify[5]) $display("Congratulations! The sixth  test you have passed!\n"); 
            end
            $display("-----------------------------------------------------\n");
      end
      $finish;
end

initial begin
  #(`CYCLE*50000);
      $display("---------------------WARRNING------------------------\n");
      $display("Simulation STOP! Maybe your circuit has some problem!\n");
      $display("Please check your ciruit again ...                   \n");
      $display("-----------------------------------------------------\n");
      $finish;
end
   
endmodule

2008/icc2008/LCD_CTRL.vcd
$date
	Sat Feb 19 13:02:57 2022
$end
$version
	ModelSim Version 10.1c
$end
$timescale
	10ps
$end
$scope module test $end
$var parameter 32 ! IMAGE_N_PAT $end
$var parameter 32 " CMD_N_PAT $end
$var parameter 32 # OUT_LENGTH $end
$var parameter 32 $ t_reset $end
$var reg 1 % clk $end
$var reg 1 & reset $end
$var reg 8 ' datain [7:0] $end
$var reg 4 ( cmd [3:0] $end
$var reg 1 ) cmd_valid $end
$var wire 1 * dataout [7] $end
$var wire 1 + dataout [6] $end
$var wire 1 , dataout [5] $end
$var wire 1 - dataout [4] $end
$var wire 1 . dataout [3] $end
$var wire 1 / dataout [2] $end
$var wire 1 0 dataout [1] $end
$var wire 1 1 dataout [0] $end
$var wire 1 2 output_valid $end
$var wire 1 3 busy $end
$var reg 8 4 out_temp [7:0] $end
$var reg 6 5 show [5:0] $end
$var reg 6 6 verify [5:0] $end
$var integer 32 7 i $end
$var integer 32 8 j $end
$var integer 32 9 out_f $end
$var integer 32 : err $end
$var integer 32 ; pass $end
$var integer 32 < pattern_num $end
$var reg 1 = over $end
$scope module top $end
$var wire 1 > clk $end
$var wire 1 ? reset $end
$var wire 1 @ datain [7] $end
$var wire 1 A datain [6] $end
$var wire 1 B datain [5] $end
$var wire 1 C datain [4] $end
$var wire 1 D datain [3] $end
$var wire 1 E datain [2] $end
$var wire 1 F datain [1] $end
$var wire 1 G datain [0] $end
$var wire 1 H cmd [3] $end
$var wire 1 I cmd [2] $end
$var wire 1 J cmd [1] $end
$var wire 1 K cmd [0] $end
$var wire 1 L cmd_valid $end
$var reg 8 M dataout [7:0] $end
$var reg 1 N output_valid $end
$var reg 1 O busy $end
$var reg 4 P originx [3:0] $end
$var reg 4 Q originy [3:0] $end
$var reg 1 R zoom $end
$var reg 2 S rot [1:0] $end
$var reg 1 T state $end
$var reg 7 U cnt [6:0] $end
$var reg 5 V discnt [4:0] $end
$upscope $end
$upscope $end
$enddefinitions $end
#0
$dumpvars
0%
0&
bx '
bx (
0)
bx 4
b111111 5
b0 6
0=
bx M
xN
xO
bx P
bx Q
xR
bx S
xT
bx U
bx V
b1101100 !
b10000010 "
b100000100000 #
b11001000 $
bx 7
bx 8
b10 9
b0 :
b0 ;
b0 <
x1
x0
x/
x.
x-
x,
x+
x*
x2
x3
0L
xK
xJ
xI
xH
xG
xF
xE
xD
xC
xB
xA
x@
0?
0>
$end
#5000
1%
1>
b1101 4
#10000
0%
0>
1&
1?
1T
0O
0N
b0 S
b100 P
b11 Q
b0 U
0R
b0 V
03
02
#15000
1%
1>
#20000
0%
0>
#25000
1%
1>
#30000
0&
0%
0?
0>
b0 7
b0 (
1)
b0 8
0K
0J
0I
0H
1L
#35000
1%
1>
0T
#40000
0%
0>
b0 '
bz (
0)
b1 8
zK
zJ
zI
zH
0G
0F
0E
0D
0C
0B
0A
0@
0L
#45000
1%
1>
1O
b1 U
13
#50000
0%
0>
b1 '
b10 8
1G
#55000
1%
1>
b10 U
#60000
0%
0>
b10 '
b11 8
0G
1F
#65000
1%
1>
b11 U
#70000
0%
0>
b11 '
b100 8
1G
#75000
1%
1>
b100 U
#80000
0%
0>
b100 '
b101 8
0G
0F
1E
#85000
1%
1>
b101 U
#90000
0%
0>
b101 '
b110 8
1G
#95000
1%
1>
b110 U
#100000
0%
0>
b110 '
b111 8
0G
1F
#105000
1%
1>
b111 U
#110000
0%
0>
b111 '
b1000 8
1G
#115000
1%
1>
b1000 U
#120000
0%
0>
b1000 '
b1001 8
0G
0F
0E
1D
#125000
1%
1>
b1001 U
#130000
0%
0>
b1001 '
b1010 8
1G
#135000
1%
1>
b1010 U
#140000
0%
0>
b1010 '
b1011 8
0G
1F
#145000
1%
1>
b1011 U
#150000
0%
0>
b1011 '
b1100 8
1G
#155000
1%
1>
b1100 U
#160000
0%
0>
b1100 '
b1101 8
0G
0F
1E
#165000
1%
1>
b1101 U
#170000
0%
0>
b1101 '
b1110 8
1G
#175000
1%
1>
b1110 U
#180000
0%
0>
b1110 '
b1111 8
0G
1F
#185000
1%
1>
b1111 U
#190000
0%
0>
b1111 '
b10000 8
1G
#195000
1%
1>
b10000 U
#200000
0%
0>
b10000 '
b10001 8
0G
0F
0E
0D
1C
#205000
1%
1>
b10001 U
#210000
0%
0>
b10001 '
b10010 8
1G
#215000
1%
1>
b10010 U
#220000
0%
0>
b10010 '
b10011 8
0G
1F
#225000
1%
1>
b10011 U
#230000
0%
0>
b10011 '
b10100 8
1G
#235000
1%
1>
b10100 U
#240000
0%
0>
b10100 '
b10101 8
0G
0F
1E
#245000
1%
1>
b10101 U
#250000
0%
0>
b10101 '
b10110 8
1G
#255000
1%
1>
b10110 U
#260000
0%
0>
b10110 '
b10111 8
0G
1F
#265000
1%
1>
b10111 U
#270000
0%
0>
b10111 '
b11000 8
1G
#275000
1%
1>
b11000 U
#280000
0%
0>
b11000 '
b11001 8
0G
0F
0E
1D
#285000
1%
1>
b11001 U
#290000
0%
0>
b11001 '
b11010 8
1G
#295000
1%
1>
b11010 U
#300000
0%
0>
b11010 '
b11011 8
0G
1F
#305000
1%
1>
b11011 U
#310000
0%
0>
b11011 '
b11100 8
1G
#315000
1%
1>
b11100 U
#320000
0%
0>
b11100 '
b11101 8
0G
0F
1E
#325000
1%
1>
b11101 U
#330000
0%
0>
b11101 '
b11110 8
1G
#335000
1%
1>
b11110 U
#340000
0%
0>
b11110 '
b11111 8
0G
1F
#345000
1%
1>
b11111 U
#350000
0%
0>
b11111 '
b100000 8
1G
#355000
1%
1>
b100000 U
#360000
0%
0>
b100000 '
b100001 8
0G
0F
0E
0D
0C
1B
#365000
1%
1>
b100001 U
#370000
0%
0>
b100001 '
b100010 8
1G
#375000
1%
1>
b100010 U
#380000
0%
0>
b100010 '
b100011 8
0G
1F
#385000
1%
1>
b100011 U
#390000
0%
0>
b100011 '
b100100 8
1G
#395000
1%
1>
b100100 U
#400000
0%
0>
b100100 '
b100101 8
0G
0F
1E
#405000
1%
1>
b100101 U
#410000
0%
0>
b100101 '
b100110 8
1G
#415000
1%
1>
b100110 U
#420000
0%
0>
b100110 '
b100111 8
0G
1F
#425000
1%
1>
b100111 U
#430000
0%
0>
b100111 '
b101000 8
1G
#435000
1%
1>
b101000 U
#440000
0%
0>
b101000 '
b101001 8
0G
0F
0E
1D
#445000
1%
1>
b101001 U
#450000
0%
0>
b101001 '
b101010 8
1G
#455000
1%
1>
b101010 U
#460000
0%
0>
b101010 '
b101011 8
0G
1F
#465000
1%
1>
b101011 U
#470000
0%
0>
b101011 '
b101100 8
1G
#475000
1%
1>
b101100 U
#480000
0%
0>
b101100 '
b101101 8
0G
0F
1E
#485000
1%
1>
b101101 U
#490000
0%
0>
b101101 '
b101110 8
1G
#495000
1%
1>
b101110 U
#500000
0%
0>
b101110 '
b101111 8
0G
1F
#505000
1%
1>
b101111 U
#510000
0%
0>
b101111 '
b110000 8
1G
#515000
1%
1>
b110000 U
#520000
0%
0>
b110000 '
b110001 8
0G
0F
0E
0D
1C
#525000
1%
1>
b110001 U
#530000
0%
0>
b110001 '
b110010 8
1G
#535000
1%
1>
b110010 U
#540000
0%
0>
b110010 '
b110011 8
0G
1F
#545000
1%
1>
b110011 U
#550000
0%
0>
b110011 '
b110100 8
1G
#555000
1%
1>
b110100 U
#560000
0%
0>
b110100 '
b110101 8
0G
0F
1E
#565000
1%
1>
b110101 U
#570000
0%
0>
b110101 '
b110110 8
1G
#575000
1%
1>
b110110 U
#580000
0%
0>
b110110 '
b110111 8
0G
1F
#585000
1%
1>
b110111 U
#590000
0%
0>
b110111 '
b111000 8
1G
#595000
1%
1>
b111000 U
#600000
0%
0>
b111000 '
b111001 8
0G
0F
0E
1D
#605000
1%
1>
b111001 U
#610000
0%
0>
b111001 '
b111010 8
1G
#615000
1%
1>
b111010 U
#620000
0%
0>
b111010 '
b111011 8
0G
1F
#625000
1%
1>
b111011 U
#630000
0%
0>
b111011 '
b111100 8
1G
#635000
1%
1>
b111100 U
#640000
0%
0>
b111100 '
b111101 8
0G
0F
1E
#645000
1%
1>
b111101 U
#650000
0%
0>
b111101 '
b111110 8
1G
#655000
1%
1>
b111110 U
#660000
0%
0>
b111110 '
b111111 8
0G
1F
#665000
1%
1>
b111111 U
#670000
0%
0>
b111111 '
b1000000 8
1G
#675000
1%
1>
b1000000 U
#680000
0%
0>
b1000000 '
b1000001 8
0G
0F
0E
0D
0C
0B
1A
#685000
1%
1>
b1000001 U
#690000
0%
0>
b1000001 '
b1000010 8
1G
#695000
1%
1>
b1000010 U
#700000
0%
0>
b1000010 '
b1000011 8
0G
1F
#705000
1%
1>
b1000011 U
#710000
0%
0>
b1000011 '
b1000100 8
1G
#715000
1%
1>
b1000100 U
#720000
0%
0>
b1000100 '
b1000101 8
0G
0F
1E
#725000
1%
1>
b1000101 U
#730000
0%
0>
b1000101 '
b1000110 8
1G
#735000
1%
1>
b1000110 U
#740000
0%
0>
b1000110 '
b1000111 8
0G
1F
#745000
1%
1>
b1000111 U
#750000
0%
0>
b1000111 '
b1001000 8
1G
#755000
1%
1>
b1001000 U
#760000
0%
0>
b1001000 '
b1001001 8
0G
0F
0E
1D
#765000
1%
1>
b1001001 U
#770000
0%
0>
b1001001 '
b1001010 8
1G
#775000
1%
1>
b1001010 U
#780000
0%
0>
b1001010 '
b1001011 8
0G
1F
#785000
1%
1>
b1001011 U
#790000
0%
0>
b1001011 '
b1001100 8
1G
#795000
1%
1>
b1001100 U
#800000
0%
0>
b1001100 '
b1001101 8
0G
0F
1E
#805000
1%
1>
b1001101 U
#810000
0%
0>
b1001101 '
b1001110 8
1G
#815000
1%
1>
b1001110 U
#820000
0%
0>
b1001110 '
b1001111 8
0G
1F
#825000
1%
1>
b1001111 U
#830000
0%
0>
b1001111 '
b1010000 8
1G
#835000
1%
1>
b1010000 U
#840000
0%
0>
b1010000 '
b1010001 8
0G
0F
0E
0D
1C
#845000
1%
1>
b1010001 U
#850000
0%
0>
b1010001 '
b1010010 8
1G
#855000
1%
1>
b1010010 U
#860000
0%
0>
b1010010 '
b1010011 8
0G
1F
#865000
1%
1>
b1010011 U
#870000
0%
0>
b1010011 '
b1010100 8
1G
#875000
1%
1>
b1010100 U
#880000
0%
0>
b1010100 '
b1010101 8
0G
0F
1E
#885000
1%
1>
b1010101 U
#890000
0%
0>
b1010101 '
b1010110 8
1G
#895000
1%
1>
b1010110 U
#900000
0%
0>
b1010110 '
b1010111 8
0G
1F
#905000
1%
1>
b1010111 U
#910000
0%
0>
b1010111 '
b1011000 8
1G
#915000
1%
1>
b1011000 U
#920000
0%
0>
b1011000 '
b1011001 8
0G
0F
0E
1D
#925000
1%
1>
b1011001 U
#930000
0%
0>
b1011001 '
b1011010 8
1G
#935000
1%
1>
b1011010 U
#940000
0%
0>
b1011010 '
b1011011 8
0G
1F
#945000
1%
1>
b1011011 U
#950000
0%
0>
b1011011 '
b1011100 8
1G
#955000
1%
1>
b1011100 U
#960000
0%
0>
b1011100 '
b1011101 8
0G
0F
1E
#965000
1%
1>
b1011101 U
#970000
0%
0>
b1011101 '
b1011110 8
1G
#975000
1%
1>
b1011110 U
#980000
0%
0>
b1011110 '
b1011111 8
0G
1F
#985000
1%
1>
b1011111 U
#990000
0%
0>
b1011111 '
b1100000 8
1G
#995000
1%
1>
b1100000 U
#1000000
0%
0>
b1100000 '
b1100001 8
0G
0F
0E
0D
0C
1B
#1005000
1%
1>
b1100001 U
#1010000
0%
0>
b1100001 '
b1100010 8
1G
#1015000
1%
1>
b1100010 U
#1020000
0%
0>
b1100010 '
b1100011 8
0G
1F
#1025000
1%
1>
b1100011 U
#1030000
0%
0>
b1100011 '
b1100100 8
1G
#1035000
1%
1>
b1100100 U
#1040000
0%
0>
b1100100 '
b1100101 8
0G
0F
1E
#1045000
1%
1>
b1100101 U
#1050000
0%
0>
b1100101 '
b1100110 8
1G
#1055000
1%
1>
b1100110 U
#1060000
0%
0>
b1100110 '
b1100111 8
0G
1F
#1065000
1%
1>
b1100111 U
#1070000
0%
0>
b1100111 '
b1101000 8
1G
#1075000
1%
1>
b1101000 U
#1080000
0%
0>
b1101000 '
b1101001 8
0G
0F
0E
1D
#1085000
1%
1>
b1101001 U
#1090000
0%
0>
b1101001 '
b1101010 8
1G
#1095000
1%
1>
b1101010 U
#1100000
0%
0>
b1101010 '
b1101011 8
0G
1F
#1105000
1%
1>
b1101011 U
#1110000
0%
0>
b1101011 '
b1101100 8
1G
#1115000
1%
1>
b1101100 U
#1120000
0%
0>
bx '
b1101101 8
b1 7
bz '
zG
zF
zE
zD
zC
zB
zA
z@
#1125000
1%
1>
b0 U
1T
1N
b1101 M
b1 V
12
11
00
1/
1.
0-
0,
0+
0*
#1130000
0%
0>
#1135000
1%
1>
b10000 M
b10 V
b1 ;
01
0/
0.
1-
#1135100
b1 <
#1140000
0%
0>
#1145000
1%
1>
b10011 M
b11 V
b10000 4
b10 ;
11
10
#1145100
b10 <
#1150000
0%
0>
#1155000
1%
1>
b10110 M
b100 V
b10011 4
b11 ;
01
1/
#1155100
b11 <
#1160000
0%
0>
#1165000
1%
1>
b100101 M
b101 V
b10110 4
b100 ;
11
00
0-
1,
#1165100
b100 <
#1170000
0%
0>
#1175000
1%
1>
b101000 M
b110 V
b100101 4
b101 ;
01
0/
1.
#1175100
b101 <
#1180000
0%
0>
#1185000
1%
1>
b101011 M
b111 V
b101000 4
b110 ;
11
10
#1185100
b110 <
#1190000
0%
0>
#1195000
1%
1>
b101110 M
b1000 V
b101011 4
b111 ;
01
1/
#1195100
b111 <
#1200000
0%
0>
#1205000
1%
1>
b111101 M
b1001 V
b101110 4
b1000 ;
11
00
1-
#1205100
b1000 <
#1210000
0%
0>
#1215000
1%
1>
b1000000 M
b1010 V
b111101 4
b1001 ;
01
0/
0.
0-
0,
1+
#1215100
b1001 <
#1220000
0%
0>
#1225000
1%
1>
b1000011 M
b1011 V
b1000000 4
b1010 ;
11
10
#1225100
b1010 <
#1230000
0%
0>
#1235000
1%
1>
b1000110 M
b1100 V
b1000011 4
b1011 ;
01
1/
#1235100
b1011 <
#1240000
0%
0>
#1245000
1%
1>
b1010101 M
b1101 V
b1000110 4
b1100 ;
11
00
1-
#1245100
b1100 <
#1250000
0%
0>
#1255000
1%
1>
b1011000 M
b1110 V
b1010101 4
b1101 ;
01
0/
1.
#1255100
b1101 <
#1260000
0%
0>
#1265000
1%
1>
b1011011 M
b1111 V
b1011000 4
b1110 ;
11
10
#1265100
b1110 <
#1270000
0%
0>
#1275000
1%
1>
b1011110 M
b10000 V
b1011011 4
b1111 ;
01
1/
#1275100
b1111 <
#1280000
0%
0>
#1285000
1%
1>
b0 V
0N
0O
b1011110 4
b10000 ;
02
03
#1285100
b10000 <
b111110 5
b1 6
#1290000
0%
0>
b1 (
1)
1K
0J
0I
0H
1L
#1295000
1%
1>
b11 S
1O
1N
b10110 M
b1 V
b10110 4
13
12
0.
0+
#1300000
0%
0>
0)
b10 7
bz (
0L
zK
zJ
zI
zH
#1305000
1%
1>
b101110 M
b10 V
b10001 ;
1.
0-
1,
#1305100
b10001 <
#1310000
0%
0>
#1315000
1%
1>
b1000110 M
b11 V
b101110 4
b10010 ;
0.
0,
1+
#1315100
b10010 <
#1320000
0%
0>
#1325000
1%
1>
b1011110 M
b100 V
b1000110 4
b10011 ;
1.
1-
#1325100
b10011 <
#1330000
0%
0>
#1335000
1%
1>
b10011 M
b101 V
b1011110 4
b10100 ;
11
0/
0.
0+
#1335100
b10100 <
#1340000
0%
0>
#1345000
1%
1>
b101011 M
b110 V
b10011 4
b10101 ;
1.
0-
1,
#1345100
b10101 <
#1350000
0%
0>
#1355000
1%
1>
b1000011 M
b111 V
b101011 4
b10110 ;
0.
0,
1+
#1355100
b10110 <
#1360000
0%
0>
#1365000
1%
1>
b1011011 M
b1000 V
b1000011 4
b10111 ;
1.
1-
#1365100
b10111 <
#1370000
0%
0>
#1375000
1%
1>
b10000 M
b1001 V
b1011011 4
b11000 ;
01
00
0.
0+
#1375100
b11000 <
#1380000
0%
0>
#1385000
1%
1>
b101000 M
b1010 V
b10000 4
b11001 ;
1.
0-
1,
#1385100
b11001 <
#1390000
0%
0>
#1395000
1%
1>
b1000000 M
b1011 V
b101000 4
b11010 ;
0.
0,
1+
#1395100
b11010 <
