2006/src/triangle.v
module triangle (clk, reset, nt, xi, yi, busy, po, xo, yo);
input clk, reset, nt;
input [2:0] xi, yi;
output reg busy, po;
output reg [2:0] xo, yo;


reg [1:0] state, NextState;
reg [4:0] x1,y1,x2,y3;
reg [5:0] count;




parameter Initialize = 0;
parameter Determination = 1;
parameter Next_Coordinate = 2;
parameter Finish = 3;


//Sequential Circuit
always@(posedge clk or posedge reset)
begin
    if(reset)
    begin
        busy <= 0;
        po <= 0;
        count <= 0;
        state <= Initialize;
    end
    else
    begin
      state <= NextState;

      case(state)
      Initialize: begin
                      case(count)
                      0:begin
                           if(nt == 1)
                           begin
                              x1 <= xi;
                              y1 <= yi;
                              count <= 1;
                           end
                        end

                      1:begin
                           x2 <= xi;
                           count <= 2;
                        end

                      2:begin
                           y3 <= yi;
                           busy <= 1;
                           count <= 0;
                        end
                      endcase
                  end

      Determination: begin
                         if(count[2:0] >= x1 && count[5:3] >= y1 && count[2:0] <= x2 && count[5:3] <= y3)
                         begin
                              if((x2 - count[2:0])*(y3 - y1) >= (x2 - x1)*(count[5:3] - y1))
                              begin
                                  po <= 1;
                                  xo <= count[2:0];
                                  yo <= count[5:3];
                              end
                         end
                     end

      Next_Coordinate: begin
                          po <= 0;
                          count <= count + 1;
                       end

      Finish: begin
                   count <= 0;
                   busy <= 0;
              end
      endcase
    end
end


//State Machine
always@(*)
begin
    case(state)
    Initialize: begin
                    if(count == 2)
                      NextState = Determination;
                    else
                      NextState = Initialize;
                end

    Determination: begin
                      NextState = Next_Coordinate;
                   end

    Next_Coordinate: begin
                        if(count == 63)
                           NextState = Finish;
                        else
                           NextState = Determination;
                     end
    Finish: begin
                NextState = Initialize;
            end

    endcase
end
                   

endmodule

2006/src/testfixture.v
`timescale 100ps/10ps
`define CYCLE      100	// Modify your clock period here (unit: ns, resolution: 0.1ns)
`define INFILE1    "input.dat"
`define IN_LENGTH  6
`define INFILE2    "expect.dat"
`define OUT_LENGTH 28
`define SDF_FILE   "triangle.sdf"

module test;
parameter INPUT_DATA = `INFILE1;
parameter EXPECT_DATA = `INFILE2;
parameter period = `CYCLE * 10; 
reg     clk;
reg     reset;
reg     nt;
reg     [2:0] xi, yi;

wire    [2:0] xo, yo;
wire    po;
wire    busy;


integer i, j, k, l, out_f, err, pattern_num, total_num, total_cycle_num;
integer a, b, c, d;
reg [5:0]  data_base [0:`IN_LENGTH - 1];
reg [5:0]  data_base_expect [0:`OUT_LENGTH - 1];
reg [5:0]  data_tmp_expect;
reg [5:0]  data_tmp_i1, data_tmp_i2, data_tmp_i3;


triangle top(clk, reset, nt, xi, yi, busy, po, xo, yo);

//initial $sdf_annotate(`SDF_FILE,top);

initial	$readmemb(INPUT_DATA,  data_base);
initial	$readmemb(EXPECT_DATA,  data_base_expect);

initial begin
   $dumpvars();
   $dumpfile("triangle.vcd");
   
   clk   = 1'b1;
   reset = 1'b0;
   nt    = 1'b0;
   xi    = 3'bz;
   yi    = 3'bz;
   l = 0;
   i = 0;
   j = 0;
   k = 0;
   err = 0;
   pattern_num = 1 ; 
   total_num = 0 ;
end

initial begin
   out_f = $fopen("OUT.DAT");
   if (out_f == 0) begin
      $display("Output file open error !");
      $finish;
   end
end

always 
   #(period/2)  clk = ~clk;

initial begin 
   @(negedge clk)  
      reset = 1'b1;
      $display ("\n****** START to VERIFY the Triangel Rendering Enginen OPERATION ******\n");
      #(period - 0.1)
         reset = 1'b0;
   
   for(i = 0; i < `IN_LENGTH; i = i + k) begin
      if(busy == 1'b1) begin
         @(negedge clk)
            nt =1'b0;
            k  =0;
      end else begin
         k  = 3;
         // cycle 1
         @(negedge clk)
            nt = 1'b1;      
            #(`CYCLE*3)  // read x1 & y1
               data_tmp_i1 = data_base[i];
               xi = data_tmp_i1[5:3];
               yi = data_tmp_i1[2:0];
         @(posedge clk)
            #(`CYCLE*2)  // close x1 & y1 
               xi = 3'bz; 
               yi = 3'bz; 
         // cycle 2
         @(negedge clk)
            nt =1'b0;      
            #(`CYCLE*3)  // read x2 & y2
               data_tmp_i2 = data_base[i+1];
               xi = data_tmp_i2[5:3];
               yi = data_tmp_i2[2:0];
         @(posedge clk)
            #(`CYCLE*2)  // close x2 & y2 
               xi = 3'bz; 
               yi = 3'bz;
         // cycle 3
         @(negedge clk)
            #(`CYCLE*3)  // read x3 & y3
               data_tmp_i3 = data_base[i+2];
               xi = data_tmp_i3[5:3];
               yi = data_tmp_i3[2:0];
         @(posedge clk)
            #(`CYCLE*2)  // close x3 & y3 
               xi = 3'bz; 
               yi = 3'bz;
         
         $display("Waiting for the rendering operation of the triangle points with:"); 
         $display("(x1, y1)=(%h, %h)",data_tmp_i1[5:3], data_tmp_i1[2:0]); 
         $display("(x2, y2)=(%h, %h)",data_tmp_i2[5:3], data_tmp_i2[2:0]); 
         $display("(x3, y3)=(%h, %h)",data_tmp_i3[5:3], data_tmp_i3[2:0]); 
      end
   end
end 

always @(posedge clk) begin
   if (po ==1'b1) begin 
      data_tmp_expect = data_base_expect[l]; 
      if ((xo !== data_tmp_expect[5:3])|| (yo!== data_tmp_expect[2:0])) begin
         $display("ERROR at %d:xo=(%h) yo=(%h)!=expect xo=(%h), yo=(%h)",l 
         ,xo, yo, data_tmp_expect[5:3], data_tmp_expect[2:0]);
         err = err + 1 ;   
      end
      $fdisplay(out_f,"%h%h",xo,yo); 
      l = l + 1;
   end
    
   if( l == `OUT_LENGTH ) begin
      if (err == 0)
         $display("PASS! All data have been generated successfully!");
      else begin
         $display("---------------------------------------------");
         $display("There are %d errors!", err);
         $display("---------------------------------------------");
      end
      $display("---------------------------------------------");
      total_num = total_cycle_num * period; 
      $display("Total delay: %d ns", total_num );
      $display("---------------------------------------------");
      $finish;
   end
end

always @(posedge clk) begin
   if (reset == 1'b1) 
      total_cycle_num = 0 ;
   else 
      total_cycle_num = total_cycle_num + 1 ;
end 

endmodule

2006/src/dump.vcd
$date
	Thu Jan 19 23:07:09 2023
$end
$version
	ModelSim Version 10.4
$end
$timescale
	10ps
$end

$scope module test $end
$var parameter 72 ! INPUT_DATA $end
$var parameter 80 " EXPECT_DATA $end
$var parameter 32 # period $end
$var reg 1 $ clk $end
$var reg 1 % reset $end
$var reg 1 & nt $end
$var reg 3 ' xi [2:0] $end
$var reg 3 ( yi [2:0] $end
$var wire 1 ) xo [2] $end
$var wire 1 * xo [1] $end
$var wire 1 + xo [0] $end
$var wire 1 , yo [2] $end
$var wire 1 - yo [1] $end
$var wire 1 . yo [0] $end
$var wire 1 / po $end
$var wire 1 0 busy $end
$var integer 32 1 i $end
$var integer 32 2 j $end
$var integer 32 3 k $end
$var integer 32 4 l $end
$var integer 32 5 out_f $end
$var integer 32 6 err $end
$var integer 32 7 pattern_num $end
$var integer 32 8 total_num $end
$var integer 32 9 total_cycle_num $end
$var integer 32 : a $end
$var integer 32 ; b $end
$var integer 32 < c $end
$var integer 32 = d $end
$var reg 6 > data_tmp_expect [5:0] $end
$var reg 6 ? data_tmp_i1 [5:0] $end
$var reg 6 @ data_tmp_i2 [5:0] $end
$var reg 6 A data_tmp_i3 [5:0] $end

$scope module top $end
$var parameter 32 B Initialize $end
$var parameter 32 C Determination $end
$var parameter 32 D Next_Coordinate $end
$var parameter 32 E Finish $end
$var wire 1 F clk $end
$var wire 1 G reset $end
$var wire 1 H nt $end
$var wire 1 I xi [2] $end
$var wire 1 J xi [1] $end
$var wire 1 K xi [0] $end
$var wire 1 L yi [2] $end
$var wire 1 M yi [1] $end
$var wire 1 N yi [0] $end
$var reg 1 O busy $end
$var reg 1 P po $end
$var reg 3 Q xo [2:0] $end
$var reg 3 R yo [2:0] $end
$var reg 2 S state [1:0] $end
$var reg 2 T NextState [1:0] $end
$var reg 5 U x1 [4:0] $end
$var reg 5 V y1 [4:0] $end
$var reg 5 W x2 [4:0] $end
$var reg 5 X y3 [4:0] $end
$var reg 6 Y count [5:0] $end
$upscope $end
$upscope $end
$enddefinitions $end
#0
$dumpvars
1$
0%
0&
bz '
bz (
bx >
bx ?
bx @
bx A
xO
xP
bx Q
bx R
bx S
bx T
bx U
bx V
bx W
bx X
bx Y
b1111101000 #
b0 B
b1 C
b10 D
b11 E
b11010010110111001110000011101010111010000101110011001000110000101110100 !
b1100101011110000111000001100101011000110111010000101110011001000110000101110100 "
b0 1
b0 2
b0 3
b0 4
b10 5
b0 6
b1 7
b0 8
bx 9
bx :
bx ;
bx <
bx =
x+
x*
x)
x.
x-
x,
x/
x0
zN
zM
zL
zK
zJ
zI
0H
0G
1F
$end
#5000
0$
0F
1%
1G
0O
0P
b0 Y
b0 S
00
0/
b0 T
#10000
1$
1F
b0 9
#14999
0%
b11 3
0G
#15000
0$
0F
1&
1H
#18000
b1001 ?
b1 '
b1 (
1N
0M
0L
1K
0J
0I
#20000
1$
1F
b1 9
b1 U
b1 V
b1 Y
#22000
bz '
bz (
zN
zM
zL
zK
zJ
zI
#25000
0$
0F
0&
0H
#28000
b100001 @
b100 '
b1 (
1N
0M
0L
0K
0J
1I
#30000
1$
1F
b10 9
b100 W
b10 Y
b1 T
#32000
bz '
bz (
zN
zM
zL
zK
zJ
zI
#35000
0$
0F
#38000
b1111 A
b1 '
b111 (
1N
1M
1L
1K
0J
0I
#40000
1$
1F
b11 9
b1 S
b111 X
1O
b0 Y
10
b10 T
#42000
bz '
bz (
b11 1
zN
zM
zL
zK
zJ
zI
#45000
0$
0F
b0 3
#50000
1$
1F
b100 9
b10 S
b1 T
#55000
0$
0F
#60000
1$
1F
b101 9
b1 S
b1 Y
b10 T
#65000
0$
0F
#70000
1$
1F
b110 9
b10 S
b1 T
#75000
0$
0F
#80000
1$
1F
b111 9
b1 S
b10 Y
b10 T
#85000
0$
0F
#90000
1$
1F
b1000 9
b10 S
b1 T
#95000
0$
0F
#100000
1$
1F
b1001 9
b1 S
b11 Y
b10 T
#105000
0$
0F
#110000
1$
1F
b1010 9
b10 S
b1 T
#115000
0$
0F
#120000
1$
1F
b1011 9
b1 S
b100 Y
b10 T
#125000
0$
0F
#130000
1$
1F
b1100 9
b10 S
b1 T
#135000
0$
0F
#140000
1$
1F
b1101 9
b1 S
b101 Y
b10 T
#145000
0$
0F
#150000
1$
1F
b1110 9
b10 S
b1 T
#155000
0$
0F
#160000
1$
1F
b1111 9
b1 S
b110 Y
b10 T
#165000
0$
0F
#170000
1$
1F
b10000 9
b10 S
b1 T
#175000
0$
0F
#180000
1$
1F
b10001 9
b1 S
b111 Y
b10 T
#185000
0$
0F
#190000
1$
1F
b10010 9
b10 S
b1 T
#195000
0$
0F
#200000
1$
1F
b10011 9
b1 S
b1000 Y
b10 T
#205000
0$
0F
#210000
1$
1F
b10100 9
b10 S
b1 T
#215000
0$
0F
#220000
1$
1F
b10101 9
b1 S
b1001 Y
b10 T
#225000
0$
0F
#230000
1$
1F
b10110 9
b10 S
1P
b1 Q
b1 R
1/
1.
0-
0,
1+
0*
0)
b1 T
#235000
0$
0F
#240000
1$
1F
b1001 >
b1 4
b10111 9
b1 S
0P
b1010 Y
0/
b10 T
#245000
0$
0F
#250000
1$
1F
b11000 9
b10 S
1P
b10 Q
1/
0+
1*
b1 T
#255000
0$
0F
#260000
1$
1F
b10001 >
b10 4
b11001 9
b1 S
0P
b1011 Y
0/
b10 T
#265000
0$
0F
#270000
1$
1F
b11010 9
b10 S
1P
b11 Q
1/
1+
b1 T
#275000
0$
0F
#280000
1$
1F
b11001 >
b11 4
b11011 9
b1 S
0P
b1100 Y
0/
b10 T
#285000
0$
0F
#290000
1$
1F
b11100 9
b10 S
1P
b100 Q
1/
0+
0*
1)
b1 T
#295000
0$
0F
#300000
1$
1F
b100001 >
b100 4
b11101 9
b1 S
0P
b1101 Y
0/
b10 T
#305000
0$
0F
#310000
1$
1F
b11110 9
b10 S
b1 T
#315000
0$
0F
#320000
1$
1F
b11111 9
b1 S
b1110 Y
b10 T
#325000
0$
0F
#330000
1$
1F
b100000 9
b10 S
b1 T
#335000
0$
0F
#340000
1$
1F
b100001 9
b1 S
b1111 Y
b10 T
#345000
0$
0F
#350000
1$
1F
b100010 9
b10 S
b1 T
#355000
0$
0F
#360000
1$
1F
b100011 9
b1 S
b10000 Y
b10 T
#365000
0$
0F
#370000
1$
1F
b100100 9
b10 S
b1 T
#375000
0$
0F
#380000
1$
1F
b100101 9
b1 S
b10001 Y
b10 T
#385000
0$
0F
#390000
1$
1F
b100110 9
b10 S
1P
b1 Q
b10 R
1/
0.
1-
1+
0)
b1 T
#395000
0$
0F
#400000
1$
1F
b1010 >
b101 4
b100111 9
b1 S
0P
b10010 Y
0/
b10 T
#405000
0$
0F
#410000
1$
1F
b101000 9
b10 S
1P
b10 Q
1/
0+
1*
b1 T
#415000
0$
0F
#420000
1$
1F
b10010 >
b110 4
b101001 9
b1 S
0P
b10011 Y
0/
b10 T
#425000
0$
0F
#430000
1$
1F
b101010 9
b10 S
1P
b11 Q
1/
1+
b1 T
#435000
0$
0F
#440000
1$
1F
b11010 >
b111 4
b101011 9
b1 S
0P
b10100 Y
0/
b10 T
#445000
0$
0F
#450000
1$
1F
b101100 9
b10 S
b1 T
#455000
0$
0F
#460000
1$
1F
b101101 9
b1 S
b10101 Y
b10 T
#465000
0$
0F
#470000
1$
1F
b101110 9
b10 S
b1 T
#475000
0$
0F
#480000
1$
1F
b101111 9
b1 S
b10110 Y
b10 T
#485000
0$
0F
#490000
1$
1F
b110000 9
b10 S
b1 T
#495000
0$
0F
#500000
1$
1F
b110001 9
b1 S
b10111 Y
b10 T
#505000
0$
0F
#510000
1$
1F
b110010 9
b10 S
b1 T
#515000
0$
0F
#520000
1$
1F
b110011 9
b1 S
b11000 Y
b10 T
#525000
0$
0F
#530000
1$
1F
b110100 9
b10 S
b1 T
#535000
0$
0F
#540000
1$
1F
b110101 9
b1 S
b11001 Y
b10 T
#545000
0$
0F
#550000
1$
1F
b110110 9
b10 S
1P
b1 Q
b11 R
1/
1.
0*
b1 T
#555000
0$
0F
#560000
1$
1F
b1011 >
b1000 4
b110111 9
b1 S
0P
b11010 Y
0/
b10 T
#565000
0$
0F
#570000
1$
1F
b111000 9
b10 S
1P
b10 Q
1/
0+
1*
b1 T
#575000
0$
0F
#580000
1$
1F
b10011 >
b1001 4
b111001 9
b1 S
0P
b11011 Y
0/
b10 T
#585000
0$
0F
#590000
1$
1F
b111010 9
b10 S
1P
b11 Q
1/
1+
b1 T
#595000
0$
0F
#600000
1$
1F
b11011 >
b1010 4
b111011 9
b1 S
0P
b11100 Y
0/
b10 T
#605000
0$
0F
#610000
1$
1F
b111100 9
b10 S
b1 T
#615000
0$
0F
#620000
1$
1F
b111101 9
b1 S
b11101 Y
b10 T
#625000
0$
0F
#630000
1$
1F
b111110 9
b10 S
b1 T
#635000
0$
0F
#640000
1$
1F
b111111 9
b1 S
b11110 Y
b10 T
#645000
0$
0F
#650000
1$
1F
b1000000 9
b10 S
b1 T
#655000
0$
0F
#660000
1$
1F
b1000001 9
b1 S
b11111 Y
b10 T
#665000
0$
0F
#670000
1$
1F
b1000010 9
b10 S
b1 T
#675000
0$
0F
#680000
1$
1F
b1000011 9
b1 S
b100000 Y
b10 T
#685000
0$
0F
#690000
1$
1F
b1000100 9
b10 S
b1 T
#695000
0$
0F
#700000
1$
1F
b1000101 9
b1 S
b100001 Y
b10 T
#705000
0$
0F
#710000
1$
1F
b1000110 9
b10 S
1P
b1 Q
b100 R
1/
0.
0-
1,
0*
b1 T
#715000
0$
0F
#720000
1$
1F
b1100 >
b1011 4
b1000111 9
b1 S
0P
b100010 Y
0/
b10 T
#725000
0$
0F
#730000
1$
1F
b1001000 9
b10 S
1P
b10 Q
1/
0+
1*
b1 T
#735000
0$
0F
#740000
1$
1F
b10100 >
b1100 4
b1001001 9
b1 S
0P
b100011 Y
0/
b10 T
#745000
0$
0F
#750000
1$
1F
b1001010 9
b10 S
b1 T
#755000
0$
0F
#760000
1$
1F
b1001011 9
b1 S
b100100 Y
b10 T
#765000
0$
0F
#770000
1$
1F
b1001100 9
b10 S
b1 T
#775000
0$
0F
#780000
1$
1F
b1001101 9
b1 S
b100101 Y
b10 T
#785000
0$
0F
#790000
1$
1F
b1001110 9
b10 S
b1 T
#795000
0$
0F
#800000
1$
1F
b1001111 9
b1 S
b100110 Y
b10 T
#805000
0$
0F
#810000
1$
1F
b1010000 9
b10 S
b1 T
#815000
0$
0F
#820000
1$
1F
b1010001 9
b1 S
b100111 Y
b10 T
#825000
0$
0F
#830000
1$
1F
b1010010 9
b10 S
b1 T
#835000
0$
0F
#840000
1$
1F
b1010011 9
b1 S
b101000 Y
b10 T
#845000
0$
0F
#850000
1$
1F
b1010100 9
b10 S
b1 T
#855000
0$
0F
#860000
1$
1F
b1010101 9
b1 S
b101001 Y
b10 T
#865000
0$
0F
#870000
1$
1F
b1010110 9
b10 S
1P
b1 Q
b101 R
1/
1.
1+
0*
b1 T
#875000
0$
0F
#880000
1$
1F
b1101 >
b1101 4
b1010111 9
b1 S
0P
b101010 Y
0/
b10 T
#885000
0$
0F
#890000
1$
1F
b1011000 9
b10 S
1P
b10 Q
1/
0+
1*
b1 T
#895000
0$
0F
#900000
1$
1F
b10101 >
b1110 4
b1011001 9
b1 S
0P
b101011 Y
0/
b10 T
#905000
0$
0F
#910000
1$
1F
b1011010 9
b10 S
b1 T
#915000
0$
0F
#920000
1$
1F
b1011011 9
b1 S
b101100 Y
b10 T
#925000
0$
0F
#930000
1$
1F
b1011100 9
b10 S
b1 T
#935000
0$
0F
#940000
1$
1F
b1011101 9
b1 S
b101101 Y
b10 T
#945000
0$
0F
#950000
1$
1F
b1011110 9
b10 S
b1 T
#955000
0$
0F
#960000
1$
1F
b1011111 9
b1 S
b101110 Y
b10 T
#965000
0$
0F
#970000
1$
1F
b1100000 9
b10 S
b1 T
#975000
0$
0F
#980000
1$
1F
b1100001 9
b1 S
b101111 Y
b10 T
#985000
0$
0F
#990000
1$
1F
b1100010 9
b10 S
b1 T
#995000
0$
0F
#1000000
1$
1F
b1100011 9
b1 S
b110000 Y
b10 T
#1005000
0$
0F
#1010000
1$
1F
b1100100 9
b10 S
b1 T
#1015000
0$
0F
#1020000
1$
1F
b1100101 9
b1 S
b110001 Y
b10 T
#1025000
0$
0F
#1030000
1$
1F
b1100110 9
b10 S
1P
b1 Q
b110 R
1/
0.
1-
1+
0*
b1 T
#1035000
0$
0F
#1040000
1$
1F
b1110 >
b1111 4
b1100111 9
b1 S
0P
b110010 Y
0/
b10 T
#1045000
0$
0F
#1050000
1$
1F
b1101000 9
b10 S
b1 T
#1055000
0$
0F
#1060000
1$
1F
b1101001 9
b1 S
b110011 Y
b10 T
#1065000
0$
0F
#1070000
1$
1F
b1101010 9
b10 S
b1 T
#1075000
0$
0F
#1080000
1$
1F
b1101011 9
b1 S
b110100 Y
b10 T
#1085000
0$
0F
#1090000
1$
1F
b1101100 9
b10 S
b1 T
#1095000
0$
0F
#1100000
1$
1F
b1101101 9
b1 S
b110101 Y
b10 T
#1105000
0$
0F
#1110000
1$
1F
b1101110 9
b10 S
b1 T
#1115000
0$
0F
#1120000
1$
1F
b1101111 9
b1 S
b110110 Y
b10 T
#1125000
0$
0F
#1130000
1$
1F
b1110000 9
b10 S
b1 T
#1135000
0$
0F
#1140000
1$
1F
b1110001 9
b1 S
b110111 Y
b10 T
#1145000
0$
0F
#1150000
1$
1F
b1110010 9
b10 S
b1 T
#1155000
0$
0F
#1160000
1$
1F
b1110011 9
b1 S
b111000 Y
b10 T
#1165000
0$
0F
#1170000
1$
1F
b1110100 9
b10 S
b1 T
#1175000
0$
0F
#1180000
1$
1F
b1110101 9
b1 S
b111001 Y
b10 T
#1185000
0$
0F
#1190000
1$
1F
b1110110 9
b10 S
1P
b111 R
1/
1.
b1 T
#1195000
0$
0F
#1200000
1$
1F
b1111 >
b10000 4
b1110111 9
b1 S
0P
b111010 Y
0/
b10 T
#1205000
0$
0F
#1210000
1$
1F
b1111000 9
b10 S
b1 T
#1215000
0$
0F
#1220000
1$
1F
b1111001 9
b1 S
b111011 Y
b10 T
#1225000
0$
0F
#1230000
1$
1F
b1111010 9
b10 S
b1 T
#1235000
0$
0F
#1240000
1$
1F
b1111011 9
b1 S
b111100 Y
b10 T
#1245000
0$
0F
#1250000
1$
1F
b1111100 9
b10 S
b1 T
#1255000
0$
0F
#1260000
1$
1F
b1111101 9
b1 S
b111101 Y
b10 T
#1265000
0$
0F
#1270000
1$
1F
b1111110 9
b10 S
b1 T
#1275000
0$
0F
#1280000
1$
1F
b1111111 9
b1 S
b111110 Y
b10 T
#1285000
0$
0F
#1290000
1$
1F
b10000000 9
b10 S
b1 T
#1295000
0$
0F
#1300000
1$
1F
b10000001 9
b1 S
b111111 Y
b10 T
#1305000
0$
0F
#1310000
1$
1F
b10000010 9
b10 S
b11 T
#1315000
0$
0F
#1320000
1$
1F
b10000011 9
b11 S
b0 Y
b0 T
#1325000
0$
0F
#1330000
1$
1F
b10000100 9
b0 S
0O
00
#1335000
0$
0F
b11 3
#1340000
1$
1F
b10000101 9
#1345000
0$
0F
1&
1H
#1348000
b1 '
b1 (
1N
0M
0L
1K
0J
0I
#1350000
1$
1F
b10000110 9
b1 Y
#1352000
bz '
bz (
zN
zM
zL
zK
zJ
zI
#1355000
0$
0F
0&
0H
#1358000
b111001 @
b111 '
b1 (
1N
0M
0L
1K
1J
1I
#1360000
1$
1F
b10000111 9
b111 W
b10 Y
b1 T
#1362000
bz '
bz (
zN
zM
zL
zK
zJ
zI
#1365000
0$
0F
#1368000
b1011 A
b1 '
b11 (
1N
1M
0L
1K
0J
0I
#1370000
1$
1F
b10001000 9
b1 S
b11 X
1O
b0 Y
10
b10 T
#1372000
bz '
bz (
b110 1
zN
zM
zL
zK
zJ
zI
#1375000
0$
0F
#1380000
1$
1F
b10001001 9
b10 S
b1 T
#1385000
0$
0F
#1390000
1$
1F
b10001010 9
b1 S
b1 Y
b10 T
#1395000
0$
0F
#1400000
1$
1F
b10001011 9
b10 S
b1 T
#1405000
0$
0F
#1410000
1$
1F
b10001100 9
b1 S
b10 Y
b10 T
#1415000
0$
0F
#1420000
1$
1F
b10001101 9
b10 S
b1 T
#1425000
0$
0F
#1430000
1$
1F
b10001110 9
b1 S
b11 Y
b10 T
#1435000
0$
0F
#1440000
1$
1F
b10001111 9
b10 S
b1 T
#1445000
0$
0F
#1450000
1$
1F
b10010000 9
b1 S
b100 Y
b10 T
#1455000
0$
0F
#1460000
1$
1F
b10010001 9
b10 S
b1 T
#1465000
0$
0F
#1470000
1$
1F
b10010010 9
b1 S
b101 Y
b10 T
#1475000
0$
0F
#1480000
1$
1F
b10010011 9
b10 S
b1 T
#1485000
0$
0F
#1490000
1$
1F
b10010100 9
b1 S
b110 Y
b10 T
#1495000
0$
0F
#1500000
1$
1F
b10010101 9
b10 S
b1 T
#1505000
0$
0F
#1510000
1$
1F
b10010110 9
b1 S
b111 Y
b10 T
#1515000
0$
0F
#1520000
1$
1F
b10010111 9
b10 S
b1 T
#1525000
0$
0F
#1530000
1$
1F
b10011000 9
b1 S
b1000 Y
b10 T
#1535000
0$
0F
#1540000
1$
1F
b10011001 9
b10 S
b1 T
#1545000
0$
0F
#1550000
1$
1F
b10011010 9
b1 S
b1001 Y
b10 T
#1555000
0$
0F
#1560000
1$
1F
b10011011 9
b10 S
1P
b1 R
1/
0-
0,
b1 T
#1565000
0$
0F
#1570000
1$
1F
b1001 >
b10001 4
b10011100 9
b1 S
0P
b1010 Y
0/
b10 T
#1575000
0$
0F
#1580000
1$
1F
b10011101 9
b10 S
1P
b10 Q
1/
0+
1*
b1 T
#1585000
0$
0F
#1590000
1$
1F
b10001 >
b10010 4
b10011110 9
b1 S
0P
b1011 Y
0/
b10 T
#1595000
0$
0F
#1600000
1$
1F
b10011111 9
b10 S
1P
b11 Q
1/
1+
b1 T
#1605000
0$
0F
#1610000
1$
1F
b11001 >
b10011 4
b10100000 9
b1 S
0P
b1100 Y
0/
b10 T
#1615000
0$
0F
#1620000
1$
1F
b10100001 9
b10 S
1P
b100 Q
1/
0+
0*
1)
b1 T
#1625000
0$
0F
#1630000
1$
1F
b100001 >
b10100 4
b10100010 9
b1 S
0P
b1101 Y
0/
b10 T
#1635000
0$
0F
#1640000
1$
1F
b10100011 9
b10 S
1P
b101 Q
1/
1+
b1 T
#1645000
0$
0F
#1650000
1$
1F
b101001 >
b10101 4
b10100100 9
b1 S
0P
b1110 Y
0/
b10 T
#1655000
0$
0F
#1660000
1$
1F
b10100101 9
b10 S
1P
b110 Q
1/
0+
1*
b1 T
#1665000
0$
0F
#1670000
1$
1F
b110001 >
b10110 4
b10100110 9
b1 S
0P
b1111 Y
0/
b10 T
#1675000
0$
0F
#1680000
1$
1F
b10100111 9
b10 S
1P
b111 Q
1/
1+
b1 T
#1685000
0$
0F
#1690000
1$
1F
b111001 >
b10111 4
b10101000 9
b1 S
0P
b10000 Y
0/
b10 T
#1695000
0$
0F
#1700000
1$
1F
b10101001 9
b10 S
b1 T
#1705000
0$
0F
#1710000
1$
1F
b10101010 9
b1 S
b10001 Y
b10 T
#1715000
0$
0F
#1720000
1$
1F
b10101011 9
b10 S
1P
b1 Q
b10 R
1/
0.
1-
0*
0)
b1 T
#1725000
0$
0F
#1730000
1$
1F
b1010 >
b11000 4
b10101100 9
b1 S
0P
b10010 Y
0/
b10 T
#1735000
0$
0F
#1740000
1$
1F
b10101101 9
b10 S
1P
b10 Q
1/
0+
1*
b1 T
#1745000
0$
0F
#1750000
1$
1F
b10010 >
b11001 4
b10101110 9
b1 S
0P
b10011 Y
0/
b10 T
#1755000
0$
0F
#1760000
1$
1F
b10101111 9
b10 S
1P
b11 Q
1/
1+
b1 T
#1765000
0$
0F
#1770000
1$
1F
b11010 >
b11010 4
b10110000 9
b1 S
0P
b10100 Y
0/
b10 T
#1775000
0$
0F
#1780000
1$
1F
b10110001 9
b10 S
1P
b100 Q
1/
0+
0*
1)
b1 T
#1785000
0$
0F
#1790000
1$
1F
b100010 >
b11011 4
b10110010 9
b1 S
0P
b10101 Y
0/
b10 T
#1795000
0$
0F
#1800000
1$
1F
b10110011 9
b10 S
b1 T
#1805000
0$
0F
#1810000
1$
1F
b10110100 9
b1 S
b10110 Y
b10 T
#1815000
0$
0F
#1820000
1$
1F
b10110101 9
b10 S
b1 T
#1825000
0$
0F
#1830000
1$
1F
b10110110 9
b1 S
b10111 Y
b10 T
#1835000
0$
0F
#1840000
1$
1F
b10110111 9
b10 S
b1 T
#1845000
0$
0F
#1850000
1$
1F
b10111000 9
b1 S
b11000 Y
b10 T
#1855000
0$
0F
#1860000
1$
1F
b10111001 9
b10 S
b1 T
#1865000
0$
0F
#1870000
1$
1F
b10111010 9
b1 S
b11001 Y
b10 T
#1875000
0$
0F
#1880000
1$
1F
b10111011 9
b10 S
1P
b1 Q
b11 R
1/
1.
1+
0)
b1 T
#1885000
0$
0F
#1890000
1$
1F
b1011 >
b11100 4
b101101101001111000 8
