ICC2007/lcd_ctrl.v
module LCD_CTRL(clk, reset, datain, cmd, cmd_valid, dataout, output_valid, busy);
input           clk;
input           reset;
input   [7:0]   datain;
input   [2:0]   cmd;
input           cmd_valid;
output  reg [7:0]  dataout;
output   reg    output_valid;
output   reg    busy;

reg [7:0] map [63:0];
reg [2:0] originx;
reg [2:0] originy;
reg multi;
reg [6:0] cnt;
reg [3:0] state;
reg [4:0] discnt;


always @(posedge clk or posedge reset) 
begin
    if(reset)
    begin
        originx <= 0;
        originy <= 0;
        multi <= 0;
        cnt <= 0;
        busy <= 0;
        discnt <= 0;
        output_valid <= 0;
    end
    else
    begin
        if(cmd_valid == 1 && cmd == 1 && busy == 0)   //load data
        begin
            state <= 1;
            busy <= 1;
            multi <= 0;
        end
        else if(cmd_valid == 1 && cmd == 0&& busy == 0)
        begin
            state <= 0;
            busy <= 1;
        end
        else if(cmd_valid == 1 && cmd == 2&& busy == 0)
        begin
            state <= 2;
            busy <= 1;
            multi <= 1;
        end       
        else if(cmd_valid == 1 && cmd == 3&& busy == 0)
        begin
            state <= 3;
            busy <= 1;
            multi <= 0;
        end
        else if(cmd_valid == 1 && cmd == 4&& busy == 0)
        begin
            state <= 4;
            busy <= 1;
        end
        else if(cmd_valid == 1 && cmd == 5&& busy == 0)
        begin
            state <= 5;
            busy <= 1;
        end
        else if(cmd_valid == 1 && cmd == 6&& busy == 0)
        begin
            state <= 6;
            busy <= 1;
        end
        else if(cmd_valid == 1 && cmd == 7&& busy == 0)
        begin
            state <= 7;
            busy <= 1;
        end
            if(state == 0 && busy == 1)     //display
    begin
        if(multi == 1)
        begin
        output_valid <= 1;
        if(discnt == 16)
        begin
            discnt <= 0;
            state <= 0;
            output_valid <= 0;
            busy <= 0;
        end
        else
        begin
        if(discnt == 0)
          dataout <= map[originy*8+originx];
        else if(discnt == 1) 
          dataout <= map[originy*8+originx+1];
        else if(discnt == 2) 
          dataout <= map[originy*8+originx+2];
        else if(discnt == 3) 
          dataout <= map[originy*8+originx+3];
        else if(discnt == 4) 
          dataout <= map[(originy+1)*8+originx];
        else if(discnt == 5) 
          dataout <= map[(originy+1)*8+originx+1];
        else if(discnt == 6) 
          dataout <= map[(originy+1)*8+originx+2];
        else if(discnt == 7) 
          dataout <= map[(originy+1)*8+originx+3];
        else if(discnt == 8) 
          dataout <= map[(originy+2)*8+originx];
        else if(discnt == 9) 
          dataout <= map[(originy+2)*8+originx+1];
        else if(discnt == 10) 
          dataout <= map[(originy+2)*8+originx+2];
        else if(discnt == 11) 
          dataout <= map[(originy+2)*8+originx+3];
        else if(discnt == 12) 
          dataout <= map[(originy+3)*8+originx];
        else if(discnt == 13) 
          dataout <= map[(originy+3)*8+originx+1];
        else if(discnt == 14) 
          dataout <= map[(originy+3)*8+originx+2];
        else if(discnt == 15) 
          dataout <= map[(originy+3)*8+originx+3];
        discnt <= discnt + 1;
        end
        end

        else
        begin
            output_valid <= 1;
        if(discnt == 16)
        begin
            discnt <= 0;
            state <= 0;
            output_valid <= 0;
            busy <= 0;
        end
        else
        begin
        if(discnt == 0)
          dataout <= map[0];
        else if(discnt == 1)
          dataout <= map[2];
        else if(discnt == 2)
          dataout <= map[4];
        else if(discnt == 3)
          dataout <= map[6];
        else if(discnt == 4)
          dataout <= map[16];
        else if(discnt == 5)
          dataout <= map[18];
        else if(discnt == 6)
          dataout <= map[20];
        else if(discnt == 7)
          dataout <= map[22];
        else if(discnt == 8)
          dataout <= map[32];
        else if(discnt == 9)
          dataout <= map[34];
        else if(discnt == 10)
          dataout <= map[36];
        else if(discnt == 11)
          dataout <= map[38];
        else if(discnt == 12)
          dataout <= map[48];
        else if(discnt == 13)
          dataout <= map[50];
        else if(discnt == 14)
          dataout <= map[52];
        else if(discnt == 15)
          dataout <= map[54];
        discnt <= discnt + 1;
        end
        end
    end

    else if(state == 1)    //load
    begin
        if(cnt == 64)
        begin
           state <= 0;
           cnt <= 0;
        end
        else
        begin
        busy <= 1;
        map[cnt] <= datain;
        cnt <= cnt + 1;
        end
    end

    else if(state == 2)
    begin
        originx <= 2;
        originy <= 2;
        state <= 0;
    end

    else if(state == 3)
    begin
        originx <= 0;
        originy <= 0;
        state <= 0;
    end

    else if(state == 4)
    begin
        if(multi == 1)
        begin
            if(originx == 4)
              originx <= 4;
            else
              originx <= originx + 1;
        end
        state <= 0;
    end

    else if(state == 5)
    begin
        if(multi == 1)
        begin
            if(originx == 0)
              originx <= 0;
            else
              originx <= originx - 1;
        end
        state <= 0;
    end

    else if(state == 6)
    begin
        if(multi == 1)
        begin
            if(originy == 0)
              originy <= 0;
            else
              originy <= originy - 1;
        end
        state <= 0;
    end

    else if(state == 7)
    begin
        if(multi == 1)
        begin
            if(originy == 4)
              originy <= 4;
            else
              originy <= originy + 1;
        end
        state <= 0;
    end
    end
    

end


endmodule

2007/testfixture.v
`timescale 1ns/10ps
`define CYCLE    100           	        // Modify your clock period here
`define SDFFILE  "./lcd_ctr1.sdf"	// Modify your sdf file name
`define IMAGE    "./image1.dat"         // Modify your test image file: image1.dat or image2.dat
`define CMD      "./cmd1.dat"           // Modify your test cmd file: cmd1.dat or cmd2.dat
`define EXPECT   "./out_golden1.dat"    // Modify your output golden file: out_golden1.dat or out_golden2.dat

module test;
parameter IMAGE_N_PAT = 64;
parameter CMD_N_PAT = 45;
parameter OUT_LENGTH= 720;
parameter t_reset = `CYCLE*2;

reg           clk;
reg           reset;
reg   [7:0]   datain;
reg   [2:0]   cmd;
reg           cmd_valid;
wire  [7:0]   dataout;
wire          output_valid;
wire          busy;

reg   [7:0]   image_mem [0:IMAGE_N_PAT-1];
reg   [2:0]   cmd_mem   [0:CMD_N_PAT-1];
reg   [7:0]   out_mem   [0:OUT_LENGTH-1];
reg   [7:0]   out_temp;

reg           stop;
integer       i, j, out_f, err, pattern_num;
reg           over;

   LCD_CTRL top(.clk(clk), .reset(reset), .datain(datain), 
                .cmd(cmd), .cmd_valid(cmd_valid), .dataout(dataout), 
                .output_valid(output_valid), .busy(busy));          
   


//initial $sdf_annotate(`SDFFILE, top);

initial	$readmemh (`IMAGE,  image_mem);
initial	$readmemh (`CMD,    cmd_mem);
initial	$readmemh (`EXPECT, out_mem);

initial begin
   clk         = 1'b0;
   reset       = 1'b0;
   cmd_valid   = 1'b0;
   stop        = 1'b0;  
   over        = 1'b0;
   pattern_num = 0;
   err         = 0;    
end

always begin #(`CYCLE/2) clk = ~clk; end

initial begin
$dumpfile("LCD_CTRL.vcd");
$dumpvars;
//$fsdbDumpfile("LCD_CTRL.fsdb");
//$fsdbDumpvars;

   out_f = $fopen("out.dat");
   if (out_f == 0) begin
        $display("Output file open error !");
        $finish;
   end
end


initial begin
   @(negedge clk)  reset = 1'b1;
   #t_reset        reset = 1'b0;
   
   @(negedge clk)    i=0;
   while (i <= CMD_N_PAT) begin               
      if(!busy) begin
        cmd = cmd_mem[i];
        cmd_valid = 1'b1;  
        
        if(cmd_mem[i] === 3'h1) begin    //cmd: Load data        
           for(j=0; j<=IMAGE_N_PAT; j=j+1)begin
              @(negedge clk) datain = image_mem[j];
                             cmd = 'hz; cmd_valid = 1'b0;
           end
           i = i+1;
        end
        else begin                      //cmd: other command
           @(negedge clk) datain='hz; cmd_valid = 1'b0; i = i+1;
        end       
      end 
      else begin
         datain='hz; cmd = 'hz;  cmd_valid = 0;
         @(negedge clk);
      end               
    end                                       
    stop = 1 ;      
end

always @(posedge clk)begin
   out_temp = out_mem[pattern_num];
   if(output_valid)begin
      $fdisplay(out_f,"%h", dataout);
      if(dataout !== out_temp) begin
         $display("ERROR at %d:output %h !=expect %h ",pattern_num, dataout, out_temp);
         err = err + 1 ;
      end
      pattern_num = pattern_num + 1;      
   end
   if(pattern_num === OUT_LENGTH)  over = 1'b1;
end


initial begin
      @(posedge stop)      
      if((over) || (pattern_num!='h0)) begin
         $display("---------------------------------------------\n");
         if (err == 0)  begin
            $display("All data have been generated successfully!\n");
            $display("-------------------PASS-------------------\n");
         end
         else 
            $display("There are %d errors!\n", err);
            $display("---------------------------------------------\n");
      end
      else begin
        $display("---------------------------------------------\n");
        $display("Error!!! There is no any data output ...!\n");
        $display("-------------------FAIL-------------------\n");
        $display("---------------------------------------------\n");
      end
      $finish;
end
   
endmodule

2007/LCD_CTRL.vcd
$date
	Wed Jan 11 17:33:45 2023
$end
$version
	ModelSim Version 10.1c
$end
$timescale
	10ps
$end
$scope module test $end
$var parameter 32 ! IMAGE_N_PAT $end
$var parameter 32 " CMD_N_PAT $end
$var parameter 32 # OUT_LENGTH $end
$var parameter 32 $ t_reset $end
$var reg 1 % clk $end
$var reg 1 & reset $end
$var reg 8 ' datain [7:0] $end
$var reg 3 ( cmd [2:0] $end
$var reg 1 ) cmd_valid $end
$var wire 1 * dataout [7] $end
$var wire 1 + dataout [6] $end
$var wire 1 , dataout [5] $end
$var wire 1 - dataout [4] $end
$var wire 1 . dataout [3] $end
$var wire 1 / dataout [2] $end
$var wire 1 0 dataout [1] $end
$var wire 1 1 dataout [0] $end
$var wire 1 2 output_valid $end
$var wire 1 3 busy $end
$var reg 8 4 out_temp [7:0] $end
$var reg 1 5 stop $end
$var integer 32 6 i $end
$var integer 32 7 j $end
$var integer 32 8 out_f $end
$var integer 32 9 err $end
$var integer 32 : pattern_num $end
$var reg 1 ; over $end
$scope module top $end
$var wire 1 < clk $end
$var wire 1 = reset $end
$var wire 1 > datain [7] $end
$var wire 1 ? datain [6] $end
$var wire 1 @ datain [5] $end
$var wire 1 A datain [4] $end
$var wire 1 B datain [3] $end
$var wire 1 C datain [2] $end
$var wire 1 D datain [1] $end
$var wire 1 E datain [0] $end
$var wire 1 F cmd [2] $end
$var wire 1 G cmd [1] $end
$var wire 1 H cmd [0] $end
$var wire 1 I cmd_valid $end
$var reg 8 J dataout [7:0] $end
$var reg 1 K output_valid $end
$var reg 1 L busy $end
$var reg 3 M originx [2:0] $end
$var reg 3 N originy [2:0] $end
$var reg 1 O multi $end
$var reg 7 P cnt [6:0] $end
$var reg 4 Q state [3:0] $end
$var reg 5 R discnt [4:0] $end
$upscope $end
$upscope $end
$enddefinitions $end
#0
$dumpvars
0%
0&
bx '
bx (
0)
bx 4
05
0;
bx J
xK
xL
bx M
bx N
xO
bx P
bx Q
bx R
b1000000 !
b101101 "
b1011010000 #
b11001000 $
bx 6
bx 7
b10 8
b0 9
b0 :
x1
x0
x/
x.
x-
x,
x+
x*
x2
x3
0I
xH
xG
xF
xE
xD
xC
xB
xA
x@
x?
x>
0=
0<
$end
#5000
1%
1<
b0 4
#10000
0%
0<
1&
1=
b0 M
b0 N
0O
b0 P
0L
b0 R
0K
03
02
#15000
1%
1<
#20000
0%
0<
#25000
1%
1<
#30000
0&
0%
0=
0<
b0 6
b1 (
1)
b0 7
1H
0G
0F
1I
#35000
1%
1<
b1 Q
1L
13
#40000
0%
0<
b0 '
bz (
0)
b1 7
zH
zG
zF
0E
0D
0C
0B
0A
0@
0?
0>
0I
#45000
1%
1<
b1 P
#50000
0%
0<
b1 '
b10 7
1E
#55000
1%
1<
b10 P
#60000
0%
0<
b10 '
b11 7
0E
1D
#65000
1%
1<
b11 P
#70000
0%
0<
b11 '
b100 7
1E
#75000
1%
1<
b100 P
#80000
0%
0<
b100 '
b101 7
0E
0D
1C
#85000
1%
1<
b101 P
#90000
0%
0<
b101 '
b110 7
1E
#95000
1%
1<
b110 P
#100000
0%
0<
b110 '
b111 7
0E
1D
#105000
1%
1<
b111 P
#110000
0%
0<
b111 '
b1000 7
1E
#115000
1%
1<
b1000 P
#120000
0%
0<
b1000 '
b1001 7
0E
0D
0C
1B
#125000
1%
1<
b1001 P
#130000
0%
0<
b1001 '
b1010 7
1E
#135000
1%
1<
b1010 P
#140000
0%
0<
b1010 '
b1011 7
0E
1D
#145000
1%
1<
b1011 P
#150000
0%
0<
b1011 '
b1100 7
1E
#155000
1%
1<
b1100 P
#160000
0%
0<
b1100 '
b1101 7
0E
0D
1C
#165000
1%
1<
b1101 P
#170000
0%
0<
b1101 '
b1110 7
1E
#175000
1%
1<
b1110 P
#180000
0%
0<
b1110 '
b1111 7
0E
1D
#185000
1%
1<
b1111 P
#190000
0%
0<
b1111 '
b10000 7
1E
#195000
1%
1<
b10000 P
#200000
0%
0<
b10000 '
b10001 7
0E
0D
0C
0B
1A
#205000
1%
1<
b10001 P
#210000
0%
0<
b10001 '
b10010 7
1E
#215000
1%
1<
b10010 P
#220000
0%
0<
b10010 '
b10011 7
0E
1D
#225000
1%
1<
b10011 P
#230000
0%
0<
b10011 '
b10100 7
1E
#235000
1%
1<
b10100 P
#240000
0%
0<
b10100 '
b10101 7
0E
0D
1C
#245000
1%
1<
b10101 P
#250000
0%
0<
b10101 '
b10110 7
1E
#255000
1%
1<
b10110 P
#260000
0%
0<
b10110 '
b10111 7
0E
1D
#265000
1%
1<
b10111 P
#270000
0%
0<
b10111 '
b11000 7
1E
#275000
1%
1<
b11000 P
#280000
0%
0<
b11000 '
b11001 7
0E
0D
0C
1B
#285000
1%
1<
b11001 P
#290000
0%
0<
b11001 '
b11010 7
1E
#295000
1%
1<
b11010 P
#300000
0%
0<
b11010 '
b11011 7
0E
1D
#305000
1%
1<
b11011 P
#310000
0%
0<
b11011 '
b11100 7
1E
#315000
1%
1<
b11100 P
#320000
0%
0<
b11100 '
b11101 7
0E
0D
1C
#325000
1%
1<
b11101 P
#330000
0%
0<
b11101 '
b11110 7
1E
#335000
1%
1<
b11110 P
#340000
0%
0<
b11110 '
b11111 7
0E
1D
#345000
1%
1<
b11111 P
#350000
0%
0<
b11111 '
b100000 7
1E
#355000
1%
1<
b100000 P
#360000
0%
0<
b100000 '
b100001 7
0E
0D
0C
0B
0A
1@
#365000
1%
1<
b100001 P
#370000
0%
0<
b100001 '
b100010 7
1E
#375000
1%
1<
b100010 P
#380000
0%
0<
b100010 '
b100011 7
0E
1D
#385000
1%
1<
b100011 P
#390000
0%
0<
b100011 '
b100100 7
1E
#395000
1%
1<
b100100 P
#400000
0%
0<
b100100 '
b100101 7
0E
0D
1C
#405000
1%
1<
b100101 P
#410000
0%
0<
b100101 '
b100110 7
1E
#415000
1%
1<
b100110 P
#420000
0%
0<
b100110 '
b100111 7
0E
1D
#425000
1%
1<
b100111 P
#430000
0%
0<
b100111 '
b101000 7
1E
#435000
1%
1<
b101000 P
#440000
0%
0<
b101000 '
b101001 7
0E
0D
0C
1B
#445000
1%
1<
b101001 P
#450000
0%
0<
b101001 '
b101010 7
1E
#455000
1%
1<
b101010 P
#460000
0%
0<
b101010 '
b101011 7
0E
1D
#465000
1%
1<
b101011 P
#470000
0%
0<
b101011 '
b101100 7
1E
#475000
1%
1<
b101100 P
#480000
0%
0<
b101100 '
b101101 7
0E
0D
1C
#485000
1%
1<
b101101 P
#490000
0%
0<
b101101 '
b101110 7
1E
#495000
1%
1<
b101110 P
#500000
0%
0<
b101110 '
b101111 7
0E
1D
#505000
1%
1<
b101111 P
#510000
0%
0<
b101111 '
b110000 7
1E
#515000
1%
1<
b110000 P
#520000
0%
0<
b110000 '
b110001 7
0E
0D
0C
0B
1A
#525000
1%
1<
b110001 P
#530000
0%
0<
b110001 '
b110010 7
1E
#535000
1%
1<
b110010 P
#540000
0%
0<
b110010 '
b110011 7
0E
1D
#545000
1%
1<
b110011 P
#550000
0%
0<
b110011 '
b110100 7
1E
#555000
1%
1<
b110100 P
#560000
0%
0<
b110100 '
b110101 7
0E
0D
1C
#565000
1%
1<
b110101 P
#570000
0%
0<
b110101 '
b110110 7
1E
#575000
1%
1<
b110110 P
#580000
0%
0<
b110110 '
b110111 7
0E
1D
#585000
1%
1<
b110111 P
#590000
0%
0<
b110111 '
b111000 7
1E
#595000
1%
1<
b111000 P
#600000
0%
0<
b111000 '
b111001 7
0E
0D
0C
1B
#605000
1%
1<
b111001 P
#610000
0%
0<
b111001 '
b111010 7
1E
#615000
1%
1<
b111010 P
#620000
0%
0<
b111010 '
b111011 7
0E
1D
#625000
1%
1<
b111011 P
#630000
0%
0<
b111011 '
b111100 7
1E
#635000
1%
1<
b111100 P
#640000
0%
0<
b111100 '
b111101 7
0E
0D
1C
#645000
1%
1<
b111101 P
#650000
0%
0<
b111101 '
b111110 7
1E
#655000
1%
1<
b111110 P
#660000
0%
0<
b111110 '
b111111 7
0E
1D
#665000
1%
1<
b111111 P
#670000
0%
0<
b111111 '
b1000000 7
1E
#675000
1%
1<
b1000000 P
#680000
0%
0<
bx '
b1000001 7
b1 6
bz '
zE
zD
zC
zB
zA
z@
z?
z>
#685000
1%
1<
b0 Q
b0 P
#690000
0%
0<
#695000
1%
1<
1K
b0 J
b1 R
12
01
00
0/
0.
0-
0,
0+
0*
#700000
0%
0<
#705000
1%
1<
b1 :
b10 J
b10 R
10
#710000
0%
0<
#715000
1%
1<
b10 4
b10 :
b100 J
b11 R
00
1/
#720000
0%
0<
#725000
1%
1<
b100 4
b11 :
b110 J
b100 R
10
#730000
0%
0<
#735000
1%
1<
b110 4
b100 :
b10000 J
b101 R
00
0/
1-
#740000
0%
0<
#745000
1%
1<
b10000 4
b101 :
b10010 J
b110 R
10
#750000
0%
0<
#755000
1%
1<
b10010 4
b110 :
b10100 J
b111 R
00
1/
#760000
0%
0<
#765000
1%
1<
b10100 4
b111 :
b10110 J
b1000 R
10
#770000
0%
0<
#775000
1%
1<
b10110 4
b1000 :
b100000 J
b1001 R
00
0/
0-
1,
#780000
0%
0<
#785000
1%
1<
b100000 4
b1001 :
b100010 J
b1010 R
10
#790000
0%
0<
#795000
1%
1<
b100010 4
b1010 :
b100100 J
b1011 R
00
1/
#800000
0%
0<
#805000
1%
1<
b100100 4
b1011 :
b100110 J
b1100 R
10
#810000
0%
0<
#815000
1%
1<
b100110 4
b1100 :
b110000 J
b1101 R
00
0/
1-
#820000
0%
0<
#825000
1%
1<
b110000 4
b1101 :
b110010 J
b1110 R
10
#830000
0%
0<
#835000
1%
1<
b110010 4
b1110 :
b110100 J
b1111 R
00
1/
#840000
0%
0<
#845000
1%
1<
b110100 4
b1111 :
b110110 J
b10000 R
10
#850000
0%
0<
#855000
1%
1<
b110110 4
b10000 :
b0 R
0K
0L
02
03
#860000
0%
0<
b0 (
1)
0H
0G
0F
1I
#865000
1%
1<
b0 4
1L
13
#870000
0%
0<
0)
b10 6
bz (
0I
zH
zG
zF
#875000
1%
1<
1K
b0 J
b1 R
12
00
0/
0-
0,
#880000
0%
0<
#885000
1%
1<
b10001 :
b10 J
b10 R
10
#890000
0%
0<
#895000
1%
1<
b10 4
b10010 :
b100 J
b11 R
00
1/
#900000
0%
0<
#905000
1%
1<
b100 4
b10011 :
b110 J
b100 R
10
#910000
0%
0<
#915000
1%
1<
b110 4
b10100 :
b10000 J
b101 R
00
0/
1-
#920000
0%
0<
#925000
1%
1<
b10000 4
b10101 :
b10010 J
b110 R
10
#930000
0%
0<
#935000
1%
1<
b10010 4
b10110 :
b10100 J
b111 R
00
1/
#940000
0%
0<
#945000
1%
1<
b10100 4
b10111 :
b10110 J
b1000 R
10
#950000
0%
0<
#955000
1%
1<
b10110 4
b11000 :
b100000 J
b1001 R
00
0/
0-
1,
#960000
0%
0<
#965000
1%
1<
b100000 4
b11001 :
b100010 J
b1010 R
10
#970000
0%
0<
#975000
1%
1<
b100010 4
b11010 :
b100100 J
b1011 R
00
1/
#980000
0%
0<
#985000
1%
1<
b100100 4
b11011 :
b100110 J
b1100 R
10
#990000
0%
0<
#995000
1%
1<
b100110 4
b11100 :
b110000 J
b1101 R
00
0/
1-
#1000000
0%
0<
#1005000
1%
1<
b110000 4
b11101 :
b110010 J
b1110 R
10
#1010000
0%
0<
#1015000
1%
1<
b110010 4
b11110 :
b110100 J
b1111 R
00
1/
#1020000
0%
0<
#1025000
1%
1<
b110100 4
b11111 :
b110110 J
b10000 R
10
#1030000
0%
0<
#1035000
1%
1<
b110110 4
b100000 :
b0 R
0K
0L
02
03
#1040000
0%
0<
b10 (
1)
0H
1G
0F
1I
#1045000
1%
1<
b10010 4
b10 Q
1L
1O
13
#1050000
0%
0<
0)
b11 6
bz (
0I
zH
zG
zF
#1055000
1%
1<
b10 M
b10 N
b0 Q
#1060000
0%
0<
#1065000
1%
1<
1K
b10010 J
b1 R
12
0/
0,
#1070000
0%
0<
#1075000
1%
1<
b100001 :
b10011 J
b10 R
11
#1080000
0%
0<
#1085000
1%
1<
b10011 4
b100010 :
b10100 J
b11 R
01
00
1/
#1090000
0%
0<
#1095000
1%
1<
b10100 4
b100011 :
b10101 J
b100 R
11
#1100000
0%
0<
#1105000
1%
1<
b10101 4
b100100 :
b11010 J
b101 R
01
10
0/
1.
#1110000
0%
0<
#1115000
1%
1<
b11010 4
b100101 :
b11011 J
b110 R
11
#1120000
0%
0<
#1125000
1%
1<
b11011 4
b100110 :
b11100 J
b111 R
01
00
1/
#1130000
0%
0<
#1135000
1%
1<
b11100 4
b100111 :
b11101 J
b1000 R
11
#1140000
0%
0<
#1145000
1%
1<
b11101 4
b101000 :
b100010 J
b1001 R
01
10
0/
0.
0-
1,
#1150000
0%
0<
#1155000
1%
1<
b100010 4
b101001 :
b100011 J
b1010 R
11
#1160000
0%
0<
#1165000
1%
1<
b100011 4
b101010 :
b100100 J
b1011 R
01
00
1/
#1170000
0%
0<
#1175000
1%
1<
b100100 4
b101011 :
b100101 J
b1100 R
11
#1180000
0%
0<
#1185000
1%
1<
b100101 4
b101100 :
b101010 J
b1101 R
01
10
0/
1.
#1190000
0%
0<
#1195000
1%
1<
b101010 4
b101101 :
b101011 J
b1110 R
11
#1200000
0%
0<
#1205000
1%
1<
b101011 4
b101110 :
b101100 J
b1111 R
01
00
1/
#1210000
0%
0<
#1215000
1%
1<
b101100 4
b101111 :
b101101 J
b10000 R
11
#1220000
0%
0<
#1225000
1%
1<
b101101 4
b110000 :
b0 R
0K
0L
02
03
#1230000
0%
0<
b100 (
1)
0H
0G
1F
1I
#1235000
1%
1<
b10011 4
b100 Q
1L
13
#1240000
0%
0<
0)
b100 6
bz (
0I
zH
zG
zF
#1245000
1%
1<
b11 M
b0 Q
#1250000
0%
0<
#1255000
1%
1<
1K
b10011 J
b1 R
12
10
0/
0.
1-
0,
#1260000
0%
0<
#1265000
1%
1<
b110001 :
b10100 J
b10 R
01
00
1/
#1270000
0%
0<
#1275000
1%
1<
b10100 4
b110010 :
b10101 J
b11 R
11
#1280000
0%
0<
#1285000
1%
1<
b10101 4
b110011 :
b10110 J
b100 R
01
10
#1290000
0%
0<
#1295000
1%
1<
b10110 4
b110100 :
b11011 J
b101 R
11
0/
1.
#1300000
0%
0<
#1305000
1%
1<
b11011 4
b110101 :
b11100 J
b110 R
01
00
1/
#1310000
0%
0<
#1315000
1%
1<
b11100 4
b110110 :
b11101 J
b111 R
11
#1320000
0%
0<
#1325000
1%
1<
b11101 4
b110111 :
b11110 J
b1000 R
01
10
#1330000
0%
0<
#1335000
1%
1<
b11110 4
b111000 :
b100011 J
b1001 R
11
0/
0.
0-
1,
#1340000
0%
0<
#1345000
1%
1<
b100011 4
b111001 :
b100100 J
b1010 R
01
00
1/
#1350000
0%
0<
#1355000
1%
1<
b100100 4
b111010 :
b100101 J
b1011 R
11
#1360000
0%
0<
#1365000
1%
1<
b100101 4
b111011 :
b100110 J
b1100 R
01
10
#1370000
0%
0<
#1375000
1%
1<
b100110 4
b111100 :
b101011 J
b1101 R
11
0/
1.
#1380000
0%
0<
#1385000
1%
1<
b101011 4
b111101 :
b101100 J
b1110 R
01
00
1/
#1390000
0%
0<
#1395000
1%
1<
b101100 4
b111110 :
b101101 J
b1111 R
11
#1400000
0%
0<
#1405000
1%
1<
b101101 4
b111111 :
b101110 J
b10000 R
01
10
#1410000
0%
0<
#1415000
1%
1<
b101110 4
b1000000 :
b0 R
0K
0L
02
03
#1420000
0%
0<
b111 (
1)
1H
1G
1F
1I
#1425000
1%
1<
b11011 4
b111 Q
1L
13
#1430000
0%
0<
0)
b101 6
bz (
0I
zH
zG
zF
#1435000
1%
1<
b11 N
b0 Q
#1440000
0%
0<
#1445000
1%
1<
1K
b11011 J
b1 R
12
11
0/
1-
0,
#1450000
0%
0<
#1455000
1%
1<
b1000001 :
b11100 J
b10 R
01
00
1/
#1460000
0%
0<
#1465000
1%
1<
b11100 4
b1000010 :
b11101 J
b11 R
11
#1470000
0%
0<
#1475000
1%
1<
b11101 4
b1000011 :
b11110 J
b100 R
01
10
#1480000
0%
0<
#1485000
1%
1<
b11110 4
b1000100 :
b100011 J
b101 R
11
0/
0.
0-
1,
#1490000
0%
0<
#1495000
1%
1<
b100011 4
b1000101 :
b100100 J
b110 R
01
00
1/
#1500000
0%
0<
#1505000
1%
1<
b100100 4
b1000110 :
b100101 J
b111 R
11
#1510000
0%
0<
#1515000
1%
1<
b100101 4
b1000111 :
b100110 J
b1000 R
01
10
#1520000
0%
0<
#1525000
1%
1<
b100110 4
b1001000 :
b101011 J
b1001 R
11
0/
1.
#1530000
0%
0<
#1535000
1%
1<
b101011 4
b1001001 :
b101100 J
b1010 R
01
00
1/
#1540000
0%
0<
#1545000
1%
1<
b101100 4
b1001010 :
b101101 J
b1011 R
11
#1550000
0%
0<
#1555000
1%
1<
b101101 4
b1001011 :
b101110 J
b1100 R
01
10
#1560000
0%
0<
#1565000
1%
1<
b101110 4
b1001100 :
b110011 J
b1101 R
11
0/
0.
1-
#1570000
0%
0<
#1575000
1%
1<
b110011 4
b1001101 :
b110100 J
b1110 R
01
00
1/
#1580000
0%
0<
#1585000
1%
1<
b110100 4
b1001110 :
b110101 J
b1111 R
11
#1590000
0%
0<
#1595000
1%
1<
b110101 4
b1001111 :
b110110 J
b10000 R
01
10
#1600000
0%
0<
#1605000
1%
1<
b110110 4
b1010000 :
b0 R
0K
0L
02
03
#1610000
0%
0<
b100 (
1)
0H
0G
1F
1I
#1615000
1%
1<
b11100 4
b100 Q
1L
13
#1620000
0%
0<
0)
b110 6
bz (
0I
zH
zG
zF
#1625000
1%
1<
b100 M
b0 Q
#1630000
0%
0<
#1635000
1%
1<
1K
b11100 J
b1 R
12
00
1.
0,
#1640000
0%
0<
#1645000
1%
1<
b1010001 :
b11101 J
b10 R
11
#1650000
0%
0<
#1655000
1%
1<
b11101 4
b1010010 :
b11110 J
b11 R
01
10
#1660000
0%
0<
#1665000
1%
1<
b11110 4
b1010011 :
b11111 J
b100 R
11
#1670000
0%
0<
#1675000
1%
1<
b11111 4
b1010100 :
b100100 J
b101 R
01
00
0.
0-
1,
#1680000
0%
0<
#1685000
1%
1<
b100100 4
b1010101 :
b100101 J
b110 R
11
#1690000
0%
0<
#1695000
1%
1<
b100101 4
b1010110 :
b100110 J
b111 R
01
10
#1700000
0%
0<
#1705000
1%
1<
b100110 4
b1010111 :
b100111 J
b1000 R
11
#1710000
0%
0<
#1715000
1%
1<
b100111 4
b1011000 :
b101100 J
b1001 R
01
00
1.
#1720000
0%
0<
#1725000
1%
1<
b101100 4
b1011001 :
b101101 J
b1010 R
11
#1730000
0%
0<
#1735000
1%
1<
b101101 4
b1011010 :
b101110 J
b1011 R
01
10
#1740000
0%
0<
#1745000
1%
1<
b101110 4
b1011011 :
b101111 J
b1100 R
11
#1750000
0%
0<
#1755000
1%
1<
b101111 4
b1011100 :
b110100 J
b1101 R
01
00
0.
1-
#1760000
0%
0<
#1765000
1%
1<
b110100 4
b1011101 :
b110101 J
b1110 R
11
#1770000
0%
0<
#1775000
1%
1<
b110101 4
b1011110 :
b110110 J
b1111 R
01
10
#1780000
0%
0<
#1785000
1%
1<
b110110 4
b1011111 :
b110111 J
b10000 R
11
#1790000
0%
0<
#1795000
1%
1<
b110111 4
b1100000 :
b0 R
0K
0L
02
03
#1800000
0%
0<
b111 (
1)
1H
1G
1F
1I
#1805000
1%
1<
b100100 4
b111 Q
1L
13
#1810000
0%
0<
0)
b111 6
bz (
0I
zH
zG
zF
#1815000
1%
1<
b100 N
b0 Q
#1820000
0%
0<
#1825000
1%
1<
1K
b100100 J
b1 R
12
01
00
0-
#1830000
0%
0<
#1835000
1%
1<
b1100001 :
b100101 J
b10 R
11
#1840000
0%
0<
#1845000
1%
1<
b100101 4
b1100010 :
b100110 J
b11 R
01
10
#1850000
0%
0<
#1855000
1%
1<
b100110 4
b1100011 :
b100111 J
b100 R
11
#1860000
0%
0<
#1865000
1%
1<
b100111 4
b1100100 :
b101100 J
b101 R
01
00
1.
#1870000
0%
0<
#1875000
1%
1<
b101100 4
b1100101 :
b101101 J
b110 R
11
#1880000
0%
0<
#1885000
1%
1<
b101101 4
b1100110 :
b101110 J
b111 R
01
10
#1890000
0%
0<
#1895000
1%
1<
b101110 4
b1100111 :
b101111 J
b1000 R
11
#1900000
0%
0<
#1905000
1%
1<
b101111 4
b1101000 :
b110100 J
b1001 R
01
00
0.
1-
#1910000
0%
0<
#1915000
1%
1<
b110100 4
b1101001 :
b110101 J
b1010 R
11
#1920000
0%
0<
#1925000
1%
1<
b110101 4
b1101010 :
b110110 J
b1011 R
01
10
#1930000
0%
0<
#1935000
1%
1<
b110110 4
b1101011 :
b110111 J
b1100 R
11
#1940000
0%
0<
#1945000
1%
1<
b110111 4
b1101100 :
b111100 J
b1101 R
01
00
1.
#1950000
0%
0<
#1955000
1%
1<
b111100 4
b1101101 :
b111101 J
b1110 R
11
#1960000
0%
0<
#1965000
1%
1<
b111101 4
b1101110 :
b111110 J
b1111 R
01
10
#1970000
0%
0<
#1975000
1%
1<
b111110 4
b1101111 :
b111111 J
b10000 R
11
#1980000
0%
0<
#1985000
1%
1<
b111111 4
b1110000 :
b0 R
0K
0L
02
03
#1990000
0%
0<
b111 (
1)
1H
1G
1F
1I
#1995000
1%
1<
b100100 4
b111 Q
1L
13
